{
"meta":{"test_sets":[],"test_metrics":[],"learn_metrics":[{"best_value":"Min","name":"RMSE"}],"launch_mode":"Train","parameters":"","iteration_count":1000,"learn_sets":["learn"],"name":"experiment"},
"iterations":[
{"learn":[0.9474317638],"iteration":0,"passed_time":0.1495685021,"remaining_time":149.4189336},
{"learn":[0.8882485254],"iteration":1,"passed_time":0.1589798807,"remaining_time":79.33096046},
{"learn":[0.8364373028],"iteration":2,"passed_time":0.1689467728,"remaining_time":56.14664415},
{"learn":[0.7907437784],"iteration":3,"passed_time":0.1786706931,"remaining_time":44.48900257},
{"learn":[0.7499103536],"iteration":4,"passed_time":0.1902176731,"remaining_time":37.85331694},
{"learn":[0.7141027216],"iteration":5,"passed_time":0.2032687811,"remaining_time":33.67486141},
{"learn":[0.684247379],"iteration":6,"passed_time":0.214334846,"remaining_time":30.40492887},
{"learn":[0.6579133401],"iteration":7,"passed_time":0.2247968673,"remaining_time":27.87481155},
{"learn":[0.6353970006],"iteration":8,"passed_time":0.2364827759,"remaining_time":26.03938121},
{"learn":[0.6154492953],"iteration":9,"passed_time":0.2476293239,"remaining_time":24.51530306},
{"learn":[0.5983799704],"iteration":10,"passed_time":0.2584072312,"remaining_time":23.23315924},
{"learn":[0.5849052564],"iteration":11,"passed_time":0.2705406555,"remaining_time":22.27451397},
{"learn":[0.5718789065],"iteration":12,"passed_time":0.2833536912,"remaining_time":21.51308409},
{"learn":[0.5610783804],"iteration":13,"passed_time":0.2959905169,"remaining_time":20.84618926},
{"learn":[0.5517151873],"iteration":14,"passed_time":0.3098497385,"remaining_time":20.3467995},
{"learn":[0.5420408884],"iteration":15,"passed_time":0.3224042642,"remaining_time":19.82786225},
{"learn":[0.5350355937],"iteration":16,"passed_time":0.3356509047,"remaining_time":19.40851996},
{"learn":[0.5282901416],"iteration":17,"passed_time":0.348952575,"remaining_time":19.03730159},
{"learn":[0.5228477628],"iteration":18,"passed_time":0.3620421895,"remaining_time":18.69280989},
{"learn":[0.5178320704],"iteration":19,"passed_time":0.375410873,"remaining_time":18.39513278},
{"learn":[0.5130492466],"iteration":20,"passed_time":0.388722405,"remaining_time":18.12186831},
{"learn":[0.5089059618],"iteration":21,"passed_time":0.4024010334,"remaining_time":17.88855503},
{"learn":[0.5048698675],"iteration":22,"passed_time":0.4176042379,"remaining_time":17.73910176},
{"learn":[0.5012887007],"iteration":23,"passed_time":0.4317919269,"remaining_time":17.55953836},
{"learn":[0.4986558182],"iteration":24,"passed_time":0.4455047326,"remaining_time":17.37468457},
{"learn":[0.4959435261],"iteration":25,"passed_time":0.4599814622,"remaining_time":17.23161324},
{"learn":[0.4935975017],"iteration":26,"passed_time":0.4741490905,"remaining_time":17.08692834},
{"learn":[0.4916083498],"iteration":27,"passed_time":0.4881958059,"remaining_time":16.94736869},
{"learn":[0.4898124073],"iteration":28,"passed_time":0.5016052546,"remaining_time":16.79512766},
{"learn":[0.4878715982],"iteration":29,"passed_time":0.5153181954,"remaining_time":16.66195499},
{"learn":[0.4861717129],"iteration":30,"passed_time":0.5295226705,"remaining_time":16.5518538},
{"learn":[0.4850053929],"iteration":31,"passed_time":0.5427891013,"remaining_time":16.41937031},
{"learn":[0.4834336033],"iteration":32,"passed_time":0.5591491314,"remaining_time":16.38476394},
{"learn":[0.4817235452],"iteration":33,"passed_time":0.5725814125,"remaining_time":16.26804837},
{"learn":[0.4806062872],"iteration":34,"passed_time":0.5853106348,"remaining_time":16.13785036},
{"learn":[0.4795510391],"iteration":35,"passed_time":0.5989509148,"remaining_time":16.0385745},
{"learn":[0.4784533901],"iteration":36,"passed_time":0.6135564867,"remaining_time":15.96905126},
{"learn":[0.4771952015],"iteration":37,"passed_time":0.6290371803,"remaining_time":15.92457283},
{"learn":[0.4761160961],"iteration":38,"passed_time":0.6432521406,"remaining_time":15.85039249},
{"learn":[0.4753501778],"iteration":39,"passed_time":0.6590830776,"remaining_time":15.81799386},
{"learn":[0.474691667],"iteration":40,"passed_time":0.6737765694,"remaining_time":15.7597983},
{"learn":[0.4740115098],"iteration":41,"passed_time":0.6894331129,"remaining_time":15.725641},
{"learn":[0.4731982789],"iteration":42,"passed_time":0.7035409556,"remaining_time":15.65787662},
{"learn":[0.4722348324],"iteration":43,"passed_time":0.7155762747,"remaining_time":15.54752088},
{"learn":[0.4714901525],"iteration":44,"passed_time":0.7268377217,"remaining_time":15.42511165},
{"learn":[0.4705337312],"iteration":45,"passed_time":0.7390581288,"remaining_time":15.32742293},
{"learn":[0.4696505746],"iteration":46,"passed_time":0.7504327764,"remaining_time":15.21622204},
{"learn":[0.4689258499],"iteration":47,"passed_time":0.7624794365,"remaining_time":15.12250882},
{"learn":[0.4680518545],"iteration":48,"passed_time":0.7743297791,"remaining_time":15.02831877},
{"learn":[0.467470873],"iteration":49,"passed_time":0.7856613421,"remaining_time":14.9275655},
{"learn":[0.4669134609],"iteration":50,"passed_time":0.798085486,"remaining_time":14.85064953},
{"learn":[0.4661925271],"iteration":51,"passed_time":0.8095620399,"remaining_time":14.75893873},
{"learn":[0.4656563343],"iteration":52,"passed_time":0.8209727258,"remaining_time":14.6690787},
{"learn":[0.4648963542],"iteration":53,"passed_time":0.8322711911,"remaining_time":14.58015827},
{"learn":[0.4642173464],"iteration":54,"passed_time":0.8445592939,"remaining_time":14.51106423},
{"learn":[0.4637411924],"iteration":55,"passed_time":0.857816104,"remaining_time":14.46032861},
{"learn":[0.4631902096],"iteration":56,"passed_time":0.8687554823,"remaining_time":14.37256877},
{"learn":[0.4625603811],"iteration":57,"passed_time":0.8794534471,"remaining_time":14.28353702},
{"learn":[0.4620643465],"iteration":58,"passed_time":0.890373325,"remaining_time":14.20069998},
{"learn":[0.4616910137],"iteration":59,"passed_time":0.9005366016,"remaining_time":14.10840676},
{"learn":[0.4610397723],"iteration":60,"passed_time":0.9116434193,"remaining_time":14.03333067},
{"learn":[0.4605067503],"iteration":61,"passed_time":0.9230406285,"remaining_time":13.96471144},
{"learn":[0.4598332503],"iteration":62,"passed_time":0.9342642419,"remaining_time":13.8953269},
{"learn":[0.4594427],"iteration":63,"passed_time":0.9452051917,"remaining_time":13.82362593},
{"learn":[0.4588813092],"iteration":64,"passed_time":0.9565103007,"remaining_time":13.75903279},
{"learn":[0.4585333738],"iteration":65,"passed_time":0.9671453243,"remaining_time":13.68657171},
{"learn":[0.4580442759],"iteration":66,"passed_time":0.9781012108,"remaining_time":13.62042432},
{"learn":[0.4573534319],"iteration":67,"passed_time":0.9891853687,"remaining_time":13.55765829},
{"learn":[0.4567852937],"iteration":68,"passed_time":0.9999498555,"remaining_time":13.49207704},
{"learn":[0.4564121376],"iteration":69,"passed_time":1.009671614,"remaining_time":13.41420859},
{"learn":[0.4558865341],"iteration":70,"passed_time":1.01969567,"remaining_time":13.34221518},
{"learn":[0.4554328324],"iteration":71,"passed_time":1.031052015,"remaining_time":13.28911486},
{"learn":[0.4552062402],"iteration":72,"passed_time":1.041678629,"remaining_time":13.22789164},
{"learn":[0.4549076465],"iteration":73,"passed_time":1.052340065,"remaining_time":13.16847162},
{"learn":[0.4543768952],"iteration":74,"passed_time":1.062807693,"remaining_time":13.10796154},
{"learn":[0.4541209632],"iteration":75,"passed_time":1.073920134,"remaining_time":13.05660794},
{"learn":[0.4538111441],"iteration":76,"passed_time":1.084460461,"remaining_time":12.99944163},
{"learn":[0.4531815987],"iteration":77,"passed_time":1.095443356,"remaining_time":12.94870223},
{"learn":[0.4528242792],"iteration":78,"passed_time":1.107063413,"remaining_time":12.90639751},
{"learn":[0.4524522058],"iteration":79,"passed_time":1.119504877,"remaining_time":12.87430608},
{"learn":[0.4519929223],"iteration":80,"passed_time":1.132590819,"remaining_time":12.85001188},
{"learn":[0.4516818608],"iteration":81,"passed_time":1.145610442,"remaining_time":12.82524861},
{"learn":[0.4510285249],"iteration":82,"passed_time":1.157312193,"remaining_time":12.7862082},
{"learn":[0.4507922594],"iteration":83,"passed_time":1.169440202,"remaining_time":12.75246697},
{"learn":[0.4504755817],"iteration":84,"passed_time":1.181970988,"remaining_time":12.72357005},
{"learn":[0.4501731722],"iteration":85,"passed_time":1.193978914,"remaining_time":12.68949683},
{"learn":[0.4498012902],"iteration":86,"passed_time":1.205959687,"remaining_time":12.65564591},
{"learn":[0.4494299334],"iteration":87,"passed_time":1.217272579,"remaining_time":12.61537036},
{"learn":[0.4492819485],"iteration":88,"passed_time":1.229254017,"remaining_time":12.58258887},
{"learn":[0.4488271086],"iteration":89,"passed_time":1.24040476,"remaining_time":12.54187035},
{"learn":[0.4486710911],"iteration":90,"passed_time":1.252450278,"remaining_time":12.51073959},
{"learn":[0.4481780716],"iteration":91,"passed_time":1.264650292,"remaining_time":12.48154854},
{"learn":[0.4478542905],"iteration":92,"passed_time":1.275661777,"remaining_time":12.44113153},
{"learn":[0.4474684385],"iteration":93,"passed_time":1.287084961,"remaining_time":12.40530824},
{"learn":[0.4470643732],"iteration":94,"passed_time":1.298389881,"remaining_time":12.36887202},
{"learn":[0.4465100721],"iteration":95,"passed_time":1.309707194,"remaining_time":12.33307608},
{"learn":[0.4461366785],"iteration":96,"passed_time":1.32141685,"remaining_time":12.30143727},
{"learn":[0.4457381166],"iteration":97,"passed_time":1.333334298,"remaining_time":12.27211772},
{"learn":[0.4454637073],"iteration":98,"passed_time":1.34469161,"remaining_time":12.23805192},
{"learn":[0.4449421635],"iteration":99,"passed_time":1.355744746,"remaining_time":12.20170271},
{"learn":[0.4444717082],"iteration":100,"passed_time":1.366635426,"remaining_time":12.1644084},
{"learn":[0.4441978895],"iteration":101,"passed_time":1.376884478,"remaining_time":12.12198296},
{"learn":[0.4438393885],"iteration":102,"passed_time":1.386791274,"remaining_time":12.07720167},
{"learn":[0.4434544623],"iteration":103,"passed_time":1.397530363,"remaining_time":12.04026159},
{"learn":[0.4431807484],"iteration":104,"passed_time":1.408370515,"remaining_time":12.00468201},
{"learn":[0.442675425],"iteration":105,"passed_time":1.418021998,"remaining_time":11.95954402},
{"learn":[0.4423366036],"iteration":106,"passed_time":1.427158156,"remaining_time":11.91076854},
{"learn":[0.441996699],"iteration":107,"passed_time":1.436925627,"remaining_time":11.86794129},
{"learn":[0.4416057284],"iteration":108,"passed_time":1.446306548,"remaining_time":11.82256086},
{"learn":[0.4411461899],"iteration":109,"passed_time":1.455725949,"remaining_time":11.77814632},
{"learn":[0.4406231662],"iteration":110,"passed_time":1.465233652,"remaining_time":11.73506952},
{"learn":[0.440385775],"iteration":111,"passed_time":1.474884045,"remaining_time":11.6937235},
{"learn":[0.4400482109],"iteration":112,"passed_time":1.484536181,"remaining_time":11.65295214},
{"learn":[0.439566839],"iteration":113,"passed_time":1.494492081,"remaining_time":11.61508758},
{"learn":[0.4391968914],"iteration":114,"passed_time":1.50461816,"remaining_time":11.57901801},
{"learn":[0.4387660596],"iteration":115,"passed_time":1.51451399,"remaining_time":11.5416411},
{"learn":[0.4384505648],"iteration":116,"passed_time":1.525557474,"remaining_time":11.51339529},
{"learn":[0.4381060981],"iteration":117,"passed_time":1.5372413,"remaining_time":11.49022735},
{"learn":[0.4377750257],"iteration":118,"passed_time":1.54889217,"remaining_time":11.46700842},
{"learn":[0.4374657853],"iteration":119,"passed_time":1.56076808,"remaining_time":11.44563259},
{"learn":[0.4369635228],"iteration":120,"passed_time":1.571767445,"remaining_time":11.41804615},
{"learn":[0.4365532806],"iteration":121,"passed_time":1.582337669,"remaining_time":11.38764323},
{"learn":[0.4362249018],"iteration":122,"passed_time":1.593246832,"remaining_time":11.35997945},
{"learn":[0.4359465163],"iteration":123,"passed_time":1.604233174,"remaining_time":11.33313114},
{"learn":[0.4354781536],"iteration":124,"passed_time":1.616090703,"remaining_time":11.31263492},
{"learn":[0.4349845547],"iteration":125,"passed_time":1.627502309,"remaining_time":11.28918269},
{"learn":[0.4346800972],"iteration":126,"passed_time":1.638870283,"remaining_time":11.26562013},
{"learn":[0.4342245761],"iteration":127,"passed_time":1.651111828,"remaining_time":11.24819933},
{"learn":[0.4339405075],"iteration":128,"passed_time":1.662252981,"remaining_time":11.22342904},
{"learn":[0.4336165102],"iteration":129,"passed_time":1.673281965,"remaining_time":11.19811777},
{"learn":[0.4333697419],"iteration":130,"passed_time":1.684215444,"remaining_time":11.172391},
{"learn":[0.4331182541],"iteration":131,"passed_time":1.695013823,"remaining_time":11.14599998},
{"learn":[0.4327105506],"iteration":132,"passed_time":1.706802114,"remaining_time":11.12629649},
{"learn":[0.4324544265],"iteration":133,"passed_time":1.718509585,"remaining_time":11.10618881},
{"learn":[0.4320066846],"iteration":134,"passed_time":1.729767248,"remaining_time":11.08332348},
{"learn":[0.4315841322],"iteration":135,"passed_time":1.741428194,"remaining_time":11.06319088},
{"learn":[0.43132561],"iteration":136,"passed_time":1.752212384,"remaining_time":11.03765903},
{"learn":[0.4309375901],"iteration":137,"passed_time":1.763228848,"remaining_time":11.01379179},
{"learn":[0.4307382335],"iteration":138,"passed_time":1.773512042,"remaining_time":10.9855674},
{"learn":[0.4303602675],"iteration":139,"passed_time":1.785626932,"remaining_time":10.96885115},
{"learn":[0.4300138834],"iteration":140,"passed_time":1.797345638,"remaining_time":10.94978655},
{"learn":[0.4295446492],"iteration":141,"passed_time":1.810001057,"remaining_time":10.93648526},
{"learn":[0.4291004033],"iteration":142,"passed_time":1.821700965,"remaining_time":10.91746663},
{"learn":[0.4287497966],"iteration":143,"passed_time":1.831998791,"remaining_time":10.89021504},
{"learn":[0.4284430399],"iteration":144,"passed_time":1.842219912,"remaining_time":10.862745},
{"learn":[0.4281871252],"iteration":145,"passed_time":1.852385888,"remaining_time":10.83518869},
{"learn":[0.4279141334],"iteration":146,"passed_time":1.862968535,"remaining_time":10.8102868},
{"learn":[0.4276339495],"iteration":147,"passed_time":1.87376959,"remaining_time":10.78683575},
{"learn":[0.4273067965],"iteration":148,"passed_time":1.883659157,"remaining_time":10.75834861},
{"learn":[0.4271333736],"iteration":149,"passed_time":1.893320283,"remaining_time":10.72881493},
{"learn":[0.4267978898],"iteration":150,"passed_time":1.904054093,"remaining_time":10.70557566},
{"learn":[0.4264442258],"iteration":151,"passed_time":1.915480907,"remaining_time":10.68636717},
{"learn":[0.4262332297],"iteration":152,"passed_time":1.925466725,"remaining_time":10.65928311},
{"learn":[0.4259479929],"iteration":153,"passed_time":1.93556408,"remaining_time":10.63303384},
{"learn":[0.4256803589],"iteration":154,"passed_time":1.945930737,"remaining_time":10.60846111},
{"learn":[0.4254121463],"iteration":155,"passed_time":1.955122299,"remaining_time":10.57771295},
{"learn":[0.4251203796],"iteration":156,"passed_time":1.965146553,"remaining_time":10.55171048},
{"learn":[0.4248560338],"iteration":157,"passed_time":1.974378194,"remaining_time":10.52168633},
{"learn":[0.4246574147],"iteration":158,"passed_time":1.983235777,"remaining_time":10.48994521},
{"learn":[0.4243924269],"iteration":159,"passed_time":1.992343637,"remaining_time":10.45980409},
{"learn":[0.4241993999],"iteration":160,"passed_time":2.001192838,"remaining_time":10.42857634},
{"learn":[0.4240274508],"iteration":161,"passed_time":2.010280326,"remaining_time":10.39885749},
{"learn":[0.4237639361],"iteration":162,"passed_time":2.018712351,"remaining_time":10.366026},
{"learn":[0.4235973368],"iteration":163,"passed_time":2.027901965,"remaining_time":10.33735392},
{"learn":[0.423385204],"iteration":164,"passed_time":2.037692309,"remaining_time":10.31195805},
{"learn":[0.4230199934],"iteration":165,"passed_time":2.047609767,"remaining_time":10.28738883},
{"learn":[0.4227760968],"iteration":166,"passed_time":2.057644277,"remaining_time":10.26357894},
{"learn":[0.4225623902],"iteration":167,"passed_time":2.067918344,"remaining_time":10.24111942},
{"learn":[0.4222871032],"iteration":168,"passed_time":2.077817232,"remaining_time":10.21695929},
{"learn":[0.4218474724],"iteration":169,"passed_time":2.087725645,"remaining_time":10.19301344},
{"learn":[0.4216016278],"iteration":170,"passed_time":2.097670768,"remaining_time":10.16940975},
{"learn":[0.4213672166],"iteration":171,"passed_time":2.106879327,"remaining_time":10.14241909},
{"learn":[0.4210924929],"iteration":172,"passed_time":2.11639569,"remaining_time":10.11710541},
{"learn":[0.4208530937],"iteration":173,"passed_time":2.126575999,"remaining_time":10.09512515},
{"learn":[0.420471703],"iteration":174,"passed_time":2.135999488,"remaining_time":10.06971187},
{"learn":[0.4202170129],"iteration":175,"passed_time":2.146244287,"remaining_time":10.04832553},
{"learn":[0.4199717032],"iteration":176,"passed_time":2.156366083,"remaining_time":10.02649314},
{"learn":[0.4197945818],"iteration":177,"passed_time":2.166052713,"remaining_time":10.00278275},
{"learn":[0.4195512703],"iteration":178,"passed_time":2.17541583,"remaining_time":9.977745232},
{"learn":[0.419180046],"iteration":179,"passed_time":2.185414798,"remaining_time":9.955778523},
{"learn":[0.4188701582],"iteration":180,"passed_time":2.195608759,"remaining_time":9.934826372},
{"learn":[0.4185704608],"iteration":181,"passed_time":2.204948945,"remaining_time":9.910155149},
{"learn":[0.4183279131],"iteration":182,"passed_time":2.214208237,"remaining_time":9.885290325},
{"learn":[0.4180539607],"iteration":183,"passed_time":2.22489893,"remaining_time":9.866943079},
{"learn":[0.4178695827],"iteration":184,"passed_time":2.234979629,"remaining_time":9.845991341},
{"learn":[0.4176490656],"iteration":185,"passed_time":2.244866456,"remaining_time":9.824308036},
{"learn":[0.4172883531],"iteration":186,"passed_time":2.255418164,"remaining_time":9.805641536},
{"learn":[0.4170643118],"iteration":187,"passed_time":2.265259616,"remaining_time":9.783993659},
{"learn":[0.4167215274],"iteration":188,"passed_time":2.275390745,"remaining_time":9.763713725},
{"learn":[0.4165606056],"iteration":189,"passed_time":2.284973588,"remaining_time":9.741203191},
{"learn":[0.4162587126],"iteration":190,"passed_time":2.293846758,"remaining_time":9.71582213},
{"learn":[0.4159955764],"iteration":191,"passed_time":2.30281488,"remaining_time":9.691012619},
{"learn":[0.415666426],"iteration":192,"passed_time":2.3118739,"remaining_time":9.666747342},
{"learn":[0.4153422323],"iteration":193,"passed_time":2.320782407,"remaining_time":9.642013504},
{"learn":[0.4151527812],"iteration":194,"passed_time":2.329819765,"remaining_time":9.6179739},
{"learn":[0.4150283862],"iteration":195,"passed_time":2.338815559,"remaining_time":9.593916886},
{"learn":[0.4148002108],"iteration":196,"passed_time":2.348198672,"remaining_time":9.571591543},
{"learn":[0.4145877921],"iteration":197,"passed_time":2.358047975,"remaining_time":9.551285233},
{"learn":[0.4143196168],"iteration":198,"passed_time":2.36769629,"remaining_time":9.530275017},
{"learn":[0.4141015319],"iteration":199,"passed_time":2.378033644,"remaining_time":9.512134575},
{"learn":[0.4138839342],"iteration":200,"passed_time":2.38876116,"remaining_time":9.495622722},
{"learn":[0.4135132404],"iteration":201,"passed_time":2.399405357,"remaining_time":9.478838986},
{"learn":[0.4132503885],"iteration":202,"passed_time":2.409205601,"remaining_time":9.458802285},
{"learn":[0.4130276884],"iteration":203,"passed_time":2.419095075,"remaining_time":9.439214118},
{"learn":[0.4128761734],"iteration":204,"passed_time":2.428945259,"remaining_time":9.419568199},
{"learn":[0.412707973],"iteration":205,"passed_time":2.438437792,"remaining_time":9.398638867},
{"learn":[0.4124652626],"iteration":206,"passed_time":2.447674526,"remaining_time":9.376840093},
{"learn":[0.4121395428],"iteration":207,"passed_time":2.457394836,"remaining_time":9.357003413},
{"learn":[0.4118484926],"iteration":208,"passed_time":2.467182434,"remaining_time":9.337518208},
{"learn":[0.4116492704],"iteration":209,"passed_time":2.476237946,"remaining_time":9.315371322},
{"learn":[0.4114589959],"iteration":210,"passed_time":2.485692697,"remaining_time":9.29484141},
{"learn":[0.4113244469],"iteration":211,"passed_time":2.494672941,"remaining_time":9.272652253},
{"learn":[0.4109668901],"iteration":212,"passed_time":2.504335854,"remaining_time":9.25310947},
{"learn":[0.4108550707],"iteration":213,"passed_time":2.513779141,"remaining_time":9.232852359},
{"learn":[0.4106480633],"iteration":214,"passed_time":2.524070432,"remaining_time":9.215792041},
{"learn":[0.4104466242],"iteration":215,"passed_time":2.534370489,"remaining_time":9.198826221},
{"learn":[0.4102187419],"iteration":216,"passed_time":2.544389586,"remaining_time":9.180908046},
{"learn":[0.4100239314],"iteration":217,"passed_time":2.555470907,"remaining_time":9.166872702},
{"learn":[0.4098612876],"iteration":218,"passed_time":2.566038055,"remaining_time":9.151030691},
{"learn":[0.4097043513],"iteration":219,"passed_time":2.576062197,"remaining_time":9.133311427},
{"learn":[0.4095691484],"iteration":220,"passed_time":2.586320019,"remaining_time":9.116485495},
{"learn":[0.4093259038],"iteration":221,"passed_time":2.596458953,"remaining_time":9.099302097},
{"learn":[0.4091649542],"iteration":222,"passed_time":2.606497743,"remaining_time":9.081832942},
{"learn":[0.4089957746],"iteration":223,"passed_time":2.617088827,"remaining_time":9.066343435},
{"learn":[0.4088928619],"iteration":224,"passed_time":2.626787852,"remaining_time":9.047824822},
{"learn":[0.4086434827],"iteration":225,"passed_time":2.636531258,"remaining_time":9.029536255},
{"learn":[0.4083666502],"iteration":226,"passed_time":2.647432536,"remaining_time":9.015265862},
{"learn":[0.4081695016],"iteration":227,"passed_time":2.657685715,"remaining_time":8.998830578},
{"learn":[0.4080017122],"iteration":228,"passed_time":2.66844155,"remaining_time":8.984141636},
{"learn":[0.4077627188],"iteration":229,"passed_time":2.679170814,"remaining_time":8.969397943},
{"learn":[0.4075355974],"iteration":230,"passed_time":2.689059841,"remaining_time":8.951891851},
{"learn":[0.4073938337],"iteration":231,"passed_time":2.699151017,"remaining_time":8.935120607},
{"learn":[0.4071066167],"iteration":232,"passed_time":2.709409652,"remaining_time":8.918957952},
{"learn":[0.4069191757],"iteration":233,"passed_time":2.719899974,"remaining_time":8.903604187},
{"learn":[0.4067108783],"iteration":234,"passed_time":2.729805436,"remaining_time":8.886387907},
{"learn":[0.4065692822],"iteration":235,"passed_time":2.740150612,"remaining_time":8.870657065},
{"learn":[0.4064867567],"iteration":236,"passed_time":2.74993262,"remaining_time":8.853158604},
{"learn":[0.4061396523],"iteration":237,"passed_time":2.759690841,"remaining_time":8.835648826},
{"learn":[0.4059408632],"iteration":238,"passed_time":2.771075591,"remaining_time":8.823382949},
{"learn":[0.4057262786],"iteration":239,"passed_time":2.780389089,"remaining_time":8.804565449},
{"learn":[0.4055558946],"iteration":240,"passed_time":2.790241534,"remaining_time":8.787524167},
{"learn":[0.4053754348],"iteration":241,"passed_time":2.799448763,"remaining_time":8.768521331},
{"learn":[0.4052186372],"iteration":242,"passed_time":2.809338523,"remaining_time":8.751725358},
{"learn":[0.4049891257],"iteration":243,"passed_time":2.818721239,"remaining_time":8.733414985},
{"learn":[0.4049124141],"iteration":244,"passed_time":2.82818332,"remaining_time":8.715422067},
{"learn":[0.4046896179],"iteration":245,"passed_time":2.837278725,"remaining_time":8.696374627},
{"learn":[0.4045221327],"iteration":246,"passed_time":2.847162572,"remaining_time":8.679811405},
{"learn":[0.4042806858],"iteration":247,"passed_time":2.857128912,"remaining_time":8.663552184},
{"learn":[0.4040976657],"iteration":248,"passed_time":2.866549116,"remaining_time":8.64569633},
{"learn":[0.4039339048],"iteration":249,"passed_time":2.875862607,"remaining_time":8.62758782},
{"learn":[0.4036688747],"iteration":250,"passed_time":2.885278281,"remaining_time":8.609854314},
{"learn":[0.4035346797],"iteration":251,"passed_time":2.894415366,"remaining_time":8.591359896},
{"learn":[0.4033017828],"iteration":252,"passed_time":2.904057751,"remaining_time":8.574431385},
{"learn":[0.4031261866],"iteration":253,"passed_time":2.91430292,"remaining_time":8.559330623},
{"learn":[0.4029636847],"iteration":254,"passed_time":2.923915932,"remaining_time":8.542421057},
{"learn":[0.4028327387],"iteration":255,"passed_time":2.933236238,"remaining_time":8.524717817},
{"learn":[0.4025944965],"iteration":256,"passed_time":2.942845924,"remaining_time":8.507916425},
{"learn":[0.4024411824],"iteration":257,"passed_time":2.952723887,"remaining_time":8.491942342},
{"learn":[0.4022040276],"iteration":258,"passed_time":2.963176526,"remaining_time":8.477659483},
{"learn":[0.4020268866],"iteration":259,"passed_time":2.972963207,"remaining_time":8.461510666},
{"learn":[0.4018345985],"iteration":260,"passed_time":2.982589401,"remaining_time":8.444956197},
{"learn":[0.4017449653],"iteration":261,"passed_time":2.991761167,"remaining_time":8.427174586},
{"learn":[0.4015226496],"iteration":262,"passed_time":3.001035421,"remaining_time":8.409745646},
{"learn":[0.4012896999],"iteration":263,"passed_time":3.011306453,"remaining_time":8.395157384},
{"learn":[0.4010421424],"iteration":264,"passed_time":3.021383882,"remaining_time":8.380064729},
{"learn":[0.4008947999],"iteration":265,"passed_time":3.031402485,"remaining_time":8.36484746},
{"learn":[0.4007084067],"iteration":266,"passed_time":3.041739009,"remaining_time":8.350541923},
{"learn":[0.4004948651],"iteration":267,"passed_time":3.052186322,"remaining_time":8.33656861},
{"learn":[0.4004156878],"iteration":268,"passed_time":3.062236005,"remaining_time":8.321540965},
{"learn":[0.4002133587],"iteration":269,"passed_time":3.072375282,"remaining_time":8.30679243},
{"learn":[0.3999473557],"iteration":270,"passed_time":3.082885065,"remaining_time":8.293074586},
{"learn":[0.399777518],"iteration":271,"passed_time":3.093143096,"remaining_time":8.278706521},
{"learn":[0.3995996714],"iteration":272,"passed_time":3.102935791,"remaining_time":8.263129377},
{"learn":[0.3995341375],"iteration":273,"passed_time":3.113230639,"remaining_time":8.248924979},
{"learn":[0.3993230523],"iteration":274,"passed_time":3.123276481,"remaining_time":8.234092542},
{"learn":[0.3990976824],"iteration":275,"passed_time":3.134350541,"remaining_time":8.221991999},
{"learn":[0.3989631326],"iteration":276,"passed_time":3.14496354,"remaining_time":8.20869545},
{"learn":[0.3986874258],"iteration":277,"passed_time":3.155241336,"remaining_time":8.194547643},
{"learn":[0.3985152941],"iteration":278,"passed_time":3.166213164,"remaining_time":8.182221115},
{"learn":[0.3982827915],"iteration":279,"passed_time":3.176781057,"remaining_time":8.168865576},
{"learn":[0.3981553841],"iteration":280,"passed_time":3.186698754,"remaining_time":8.153866206},
{"learn":[0.3980088415],"iteration":281,"passed_time":3.19620193,"remaining_time":8.137847466},
{"learn":[0.3977922441],"iteration":282,"passed_time":3.206287171,"remaining_time":8.123349475},
{"learn":[0.3976318655],"iteration":283,"passed_time":3.216131999,"remaining_time":8.108276447},
{"learn":[0.3974754885],"iteration":284,"passed_time":3.227120304,"remaining_time":8.096108834},
{"learn":[0.3972720084],"iteration":285,"passed_time":3.237812011,"remaining_time":8.083209006},
{"learn":[0.3971469986],"iteration":286,"passed_time":3.247405024,"remaining_time":8.06759506},
{"learn":[0.3970305666],"iteration":287,"passed_time":3.257353537,"remaining_time":8.052901801},
{"learn":[0.3968274443],"iteration":288,"passed_time":3.267282589,"remaining_time":8.038193498},
{"learn":[0.3966829291],"iteration":289,"passed_time":3.277441584,"remaining_time":8.024081119},
{"learn":[0.3965282672],"iteration":290,"passed_time":3.286909857,"remaining_time":8.00831302},
{"learn":[0.3963831801],"iteration":291,"passed_time":3.29643309,"remaining_time":7.992721329},
{"learn":[0.396176612],"iteration":292,"passed_time":3.305938379,"remaining_time":7.977127762},
{"learn":[0.3960214875],"iteration":293,"passed_time":3.315682406,"remaining_time":7.962148906},
{"learn":[0.3959151035],"iteration":294,"passed_time":3.325414164,"remaining_time":7.947176224},
{"learn":[0.3957864564],"iteration":295,"passed_time":3.334874656,"remaining_time":7.931593777},
{"learn":[0.3956784117],"iteration":296,"passed_time":3.344193059,"remaining_time":7.915716232},
{"learn":[0.3954739248],"iteration":297,"passed_time":3.353655896,"remaining_time":7.900222949},
{"learn":[0.3953236029],"iteration":298,"passed_time":3.363530357,"remaining_time":7.885735051},
{"learn":[0.3951438898],"iteration":299,"passed_time":3.37354153,"remaining_time":7.871596902},
{"learn":[0.3949966492],"iteration":300,"passed_time":3.383879983,"remaining_time":7.858246206},
{"learn":[0.3948341873],"iteration":301,"passed_time":3.394518512,"remaining_time":7.845609012},
{"learn":[0.3946786756],"iteration":302,"passed_time":3.404792084,"remaining_time":7.832145488},
{"learn":[0.3944849837],"iteration":303,"passed_time":3.415299607,"remaining_time":7.819238573},
{"learn":[0.3943348726],"iteration":304,"passed_time":3.42558609,"remaining_time":7.805843713},
{"learn":[0.3941470189],"iteration":305,"passed_time":3.43727748,"remaining_time":7.795655461},
{"learn":[0.3938670406],"iteration":306,"passed_time":3.448283167,"remaining_time":7.783909559},
{"learn":[0.393713282],"iteration":307,"passed_time":3.458662206,"remaining_time":7.77076054},
{"learn":[0.3934693291],"iteration":308,"passed_time":3.469662854,"remaining_time":7.759019521},
{"learn":[0.3932940249],"iteration":309,"passed_time":3.480901304,"remaining_time":7.74781258},
{"learn":[0.3930866127],"iteration":310,"passed_time":3.492324565,"remaining_time":7.737014872},
{"learn":[0.392945668],"iteration":311,"passed_time":3.502911006,"remaining_time":7.724367859},
{"learn":[0.3927742296],"iteration":312,"passed_time":3.514030461,"remaining_time":7.712903919},
{"learn":[0.3925858138],"iteration":313,"passed_time":3.524166036,"remaining_time":7.699292677},
{"learn":[0.3924252025],"iteration":314,"passed_time":3.534948204,"remaining_time":7.687109586},
{"learn":[0.3921252554],"iteration":315,"passed_time":3.545704361,"remaining_time":7.67487906},
{"learn":[0.3919207016],"iteration":316,"passed_time":3.556724339,"remaining_time":7.663226258},
{"learn":[0.3918116621],"iteration":317,"passed_time":3.568291284,"remaining_time":7.65275049},
{"learn":[0.3916325244],"iteration":318,"passed_time":3.581237114,"remaining_time":7.64521152},
{"learn":[0.391497553],"iteration":319,"passed_time":3.594453422,"remaining_time":7.638213521},
{"learn":[0.391361834],"iteration":320,"passed_time":3.607154769,"remaining_time":7.630087502},
{"learn":[0.3912010298],"iteration":321,"passed_time":3.619725824,"remaining_time":7.621658722},
{"learn":[0.3910022875],"iteration":322,"passed_time":3.630748408,"remaining_time":7.609958738},
{"learn":[0.3907862721],"iteration":323,"passed_time":3.643161605,"remaining_time":7.601164337},
{"learn":[0.3905661598],"iteration":324,"passed_time":3.65486835,"remaining_time":7.590880419},
{"learn":[0.3904406141],"iteration":325,"passed_time":3.666364323,"remaining_time":7.580152006},
{"learn":[0.3902607353],"iteration":326,"passed_time":3.677301858,"remaining_time":7.568269573},
{"learn":[0.390046362],"iteration":327,"passed_time":3.688895548,"remaining_time":7.557737219},
{"learn":[0.3898838025],"iteration":328,"passed_time":3.700281246,"remaining_time":7.546774213},
{"learn":[0.3897478127],"iteration":329,"passed_time":3.712774226,"remaining_time":7.538056762},
{"learn":[0.3896425566],"iteration":330,"passed_time":3.725842025,"remaining_time":7.530478293},
{"learn":[0.3895102806],"iteration":331,"passed_time":3.738509096,"remaining_time":7.522060471},
{"learn":[0.389355441],"iteration":332,"passed_time":3.751457935,"remaining_time":7.51418151},
{"learn":[0.389168191],"iteration":333,"passed_time":3.765946571,"remaining_time":7.509342563},
{"learn":[0.3890882245],"iteration":334,"passed_time":3.778308686,"remaining_time":7.500224705},
{"learn":[0.3889862678],"iteration":335,"passed_time":3.791983284,"remaining_time":7.493681253},
{"learn":[0.3887779647],"iteration":336,"passed_time":3.805664196,"remaining_time":7.487107899},
{"learn":[0.3886897986],"iteration":337,"passed_time":3.817942866,"remaining_time":7.477746087},
{"learn":[0.3884754485],"iteration":338,"passed_time":3.829245816,"remaining_time":7.466464556},
{"learn":[0.3882351566],"iteration":339,"passed_time":3.840382826,"remaining_time":7.45486078},
{"learn":[0.3880903046],"iteration":340,"passed_time":3.851020996,"remaining_time":7.442295707},
{"learn":[0.3880408842],"iteration":341,"passed_time":3.860687004,"remaining_time":7.427871487},
{"learn":[0.3878032171],"iteration":342,"passed_time":3.87137115,"remaining_time":7.415425205},
{"learn":[0.3874971463],"iteration":343,"passed_time":3.881566144,"remaining_time":7.402056367},
{"learn":[0.3873795386],"iteration":344,"passed_time":3.891402074,"remaining_time":7.388024227},
{"learn":[0.3871520456],"iteration":345,"passed_time":3.901532484,"remaining_time":7.374572962},
{"learn":[0.3869995283],"iteration":346,"passed_time":3.912138552,"remaining_time":7.36203595},
{"learn":[0.3867898326],"iteration":347,"passed_time":3.92220929,"remaining_time":7.348507061},
{"learn":[0.3865139376],"iteration":348,"passed_time":3.931799196,"remaining_time":7.334101078},
{"learn":[0.3863189342],"iteration":349,"passed_time":3.94191261,"remaining_time":7.320694847},
{"learn":[0.3862023266],"iteration":350,"passed_time":3.951013334,"remaining_time":7.305434911},
{"learn":[0.3859421945],"iteration":351,"passed_time":3.96006821,"remaining_time":7.290125569},
{"learn":[0.3857648118],"iteration":352,"passed_time":3.969359883,"remaining_time":7.275285678},
{"learn":[0.3856019854],"iteration":353,"passed_time":3.978331301,"remaining_time":7.259892714},
{"learn":[0.3854416175],"iteration":354,"passed_time":3.987654781,"remaining_time":7.245175588},
{"learn":[0.385202763],"iteration":355,"passed_time":3.996419053,"remaining_time":7.229477164},
{"learn":[0.3851558657],"iteration":356,"passed_time":4.005130652,"remaining_time":7.213722715},
{"learn":[0.3850321886],"iteration":357,"passed_time":4.013295292,"remaining_time":7.197026753},
{"learn":[0.3848515992],"iteration":358,"passed_time":4.022735398,"remaining_time":7.182655683},
{"learn":[0.3846535228],"iteration":359,"passed_time":4.031836733,"remaining_time":7.167709747},
{"learn":[0.3844294346],"iteration":360,"passed_time":4.041336205,"remaining_time":7.153500928},
{"learn":[0.3842639716],"iteration":361,"passed_time":4.050838395,"remaining_time":7.139322917},
{"learn":[0.3841154766],"iteration":362,"passed_time":4.060415758,"remaining_time":7.125302584},
{"learn":[0.3839352175],"iteration":363,"passed_time":4.07004936,"remaining_time":7.111404926},
{"learn":[0.3838244957],"iteration":364,"passed_time":4.080195258,"remaining_time":7.098421887},
{"learn":[0.3836482588],"iteration":365,"passed_time":4.089564164,"remaining_time":7.084108416},
{"learn":[0.3835076151],"iteration":366,"passed_time":4.099167751,"remaining_time":7.070226667},
{"learn":[0.3833902926],"iteration":367,"passed_time":4.108706106,"remaining_time":7.056256139},
{"learn":[0.3832869637],"iteration":368,"passed_time":4.117838388,"remaining_time":7.041615237},
{"learn":[0.3831093823],"iteration":369,"passed_time":4.127826837,"remaining_time":7.028461911},
{"learn":[0.3828360329],"iteration":370,"passed_time":4.137961992,"remaining_time":7.015574375},
{"learn":[0.3825985952],"iteration":371,"passed_time":4.147739058,"remaining_time":7.002097119},
{"learn":[0.3825028138],"iteration":372,"passed_time":4.157785502,"remaining_time":6.989092519},
{"learn":[0.382376001],"iteration":373,"passed_time":4.167943315,"remaining_time":6.976290148},
{"learn":[0.3822376356],"iteration":374,"passed_time":4.177921936,"remaining_time":6.963203226},
{"learn":[0.3820734462],"iteration":375,"passed_time":4.187515013,"remaining_time":6.949493},
{"learn":[0.3818953294],"iteration":376,"passed_time":4.196974776,"remaining_time":6.935584311},
{"learn":[0.3817205808],"iteration":377,"passed_time":4.20615286,"remaining_time":6.921235659},
{"learn":[0.3815660068],"iteration":378,"passed_time":4.215546389,"remaining_time":6.907267302},
{"learn":[0.3813788428],"iteration":379,"passed_time":4.225387773,"remaining_time":6.894053734},
{"learn":[0.3812906626],"iteration":380,"passed_time":4.235015702,"remaining_time":6.880511075},
{"learn":[0.3811344836],"iteration":381,"passed_time":4.244091536,"remaining_time":6.866095732},
{"learn":[0.3810241731],"iteration":382,"passed_time":4.253931545,"remaining_time":6.85293933},
{"learn":[0.3808344617],"iteration":383,"passed_time":4.263214681,"remaining_time":6.838906883},
{"learn":[0.3806981326],"iteration":384,"passed_time":4.272220435,"remaining_time":6.82445602},
{"learn":[0.3805694147],"iteration":385,"passed_time":4.28118351,"remaining_time":6.809965479},
{"learn":[0.3804171143],"iteration":386,"passed_time":4.290183502,"remaining_time":6.795561981},
{"learn":[0.3802734129],"iteration":387,"passed_time":4.29929243,"remaining_time":6.781358163},
{"learn":[0.3800389019],"iteration":388,"passed_time":4.308393527,"remaining_time":6.767168239},
{"learn":[0.3799510457],"iteration":389,"passed_time":4.3169995,"remaining_time":6.752229988},
{"learn":[0.379746166],"iteration":390,"passed_time":4.326096214,"remaining_time":6.738088477},
{"learn":[0.3795394582],"iteration":391,"passed_time":4.336138975,"remaining_time":6.725440042},
{"learn":[0.3793740056],"iteration":392,"passed_time":4.345488284,"remaining_time":6.711733813},
{"learn":[0.379240723],"iteration":393,"passed_time":4.354965602,"remaining_time":6.698246586},
{"learn":[0.3791067508],"iteration":394,"passed_time":4.365247414,"remaining_time":6.686011863},
{"learn":[0.3789973804],"iteration":395,"passed_time":4.375184193,"remaining_time":6.673260739},
{"learn":[0.3789310748],"iteration":396,"passed_time":4.384877345,"remaining_time":6.660153751},
{"learn":[0.3786931505],"iteration":397,"passed_time":4.395403783,"remaining_time":6.648324315},
{"learn":[0.3785766007],"iteration":398,"passed_time":4.405680553,"remaining_time":6.636125344},
{"learn":[0.3784348468],"iteration":399,"passed_time":4.416214712,"remaining_time":6.624322068},
{"learn":[0.3783681923],"iteration":400,"passed_time":4.425926857,"remaining_time":6.611297225},
{"learn":[0.3782018522],"iteration":401,"passed_time":4.435568498,"remaining_time":6.598183984},
{"learn":[0.3780392363],"iteration":402,"passed_time":4.445587112,"remaining_time":6.585646417},
{"learn":[0.3779331613],"iteration":403,"passed_time":4.455130466,"remaining_time":6.572420192},
{"learn":[0.3778396522],"iteration":404,"passed_time":4.465646411,"remaining_time":6.560641023},
{"learn":[0.3777510757],"iteration":405,"passed_time":4.475336562,"remaining_time":6.547659896},
{"learn":[0.3776293989],"iteration":406,"passed_time":4.485303994,"remaining_time":6.53509894},
{"learn":[0.3774768782],"iteration":407,"passed_time":4.494681106,"remaining_time":6.521694153},
{"learn":[0.3773890811],"iteration":408,"passed_time":4.504204753,"remaining_time":6.508520804},
{"learn":[0.3772346031],"iteration":409,"passed_time":4.513585689,"remaining_time":6.495159895},
{"learn":[0.3770371671],"iteration":410,"passed_time":4.524087871,"remaining_time":6.483425197},
{"learn":[0.3769314701],"iteration":411,"passed_time":4.534627898,"remaining_time":6.471750495},
{"learn":[0.3768224045],"iteration":412,"passed_time":4.544965539,"remaining_time":6.459793636},
{"learn":[0.376742342],"iteration":413,"passed_time":4.555261457,"remaining_time":6.44778554},
{"learn":[0.3765939522],"iteration":414,"passed_time":4.565448279,"remaining_time":6.435631911},
{"learn":[0.3764146199],"iteration":415,"passed_time":4.57605634,"remaining_time":6.424079093},
{"learn":[0.3763145623],"iteration":416,"passed_time":4.586303489,"remaining_time":6.412026221},
{"learn":[0.3761413818],"iteration":417,"passed_time":4.596996472,"remaining_time":6.400602743},
{"learn":[0.3760156673],"iteration":418,"passed_time":4.607106157,"remaining_time":6.388373931},
{"learn":[0.3758999876],"iteration":419,"passed_time":4.616797216,"remaining_time":6.375577107},
{"learn":[0.3757353046],"iteration":420,"passed_time":4.627318519,"remaining_time":6.363936871},
{"learn":[0.375642476],"iteration":421,"passed_time":4.637536746,"remaining_time":6.351886823},
{"learn":[0.3754869576],"iteration":422,"passed_time":4.647544132,"remaining_time":6.339557835},
{"learn":[0.3753581375],"iteration":423,"passed_time":4.658072556,"remaining_time":6.327947623},
{"learn":[0.3752264309],"iteration":424,"passed_time":4.667939428,"remaining_time":6.315447461},
{"learn":[0.375111211],"iteration":425,"passed_time":4.678561787,"remaining_time":6.303977619},
{"learn":[0.3749611805],"iteration":426,"passed_time":4.689335361,"remaining_time":6.292714664},
{"learn":[0.3748583235],"iteration":427,"passed_time":4.699503007,"remaining_time":6.280644205},
{"learn":[0.3747113018],"iteration":428,"passed_time":4.709797033,"remaining_time":6.26875083},
{"learn":[0.3745389762],"iteration":429,"passed_time":4.719993585,"remaining_time":6.256735683},
{"learn":[0.3744152332],"iteration":430,"passed_time":4.730336009,"remaining_time":6.244921553},
{"learn":[0.3742589995],"iteration":431,"passed_time":4.741015393,"remaining_time":6.233557276},
{"learn":[0.3741822717],"iteration":432,"passed_time":4.75186159,"remaining_time":6.222414599},
{"learn":[0.3740714069],"iteration":433,"passed_time":4.762871724,"remaining_time":6.211487087},
{"learn":[0.3738524742],"iteration":434,"passed_time":4.773684313,"remaining_time":6.200302613},
{"learn":[0.3737180534],"iteration":435,"passed_time":4.784773847,"remaining_time":6.189478096},
{"learn":[0.3736271483],"iteration":436,"passed_time":4.794844537,"remaining_time":6.177339758},
{"learn":[0.3734468428],"iteration":437,"passed_time":4.804888107,"remaining_time":6.165176064},
{"learn":[0.3733297799],"iteration":438,"passed_time":4.814383982,"remaining_time":6.152322127},
{"learn":[0.3732186506],"iteration":439,"passed_time":4.82388002,"remaining_time":6.139483662},
{"learn":[0.3730935131],"iteration":440,"passed_time":4.833088747,"remaining_time":6.126296167},
{"learn":[0.372874407],"iteration":441,"passed_time":4.842579946,"remaining_time":6.11348328},
{"learn":[0.3727135596],"iteration":442,"passed_time":4.854918884,"remaining_time":6.104265955},
{"learn":[0.3725941854],"iteration":443,"passed_time":4.865715313,"remaining_time":6.093102959},
{"learn":[0.3724174633],"iteration":444,"passed_time":4.876273693,"remaining_time":6.081644718},
{"learn":[0.372305449],"iteration":445,"passed_time":4.88667579,"remaining_time":6.069996384},
{"learn":[0.3721348859],"iteration":446,"passed_time":4.897294374,"remaining_time":6.058621452},
{"learn":[0.3720258063],"iteration":447,"passed_time":4.907438438,"remaining_time":6.046665218},
{"learn":[0.3719304082],"iteration":448,"passed_time":4.917385997,"remaining_time":6.034475911},
{"learn":[0.3718858086],"iteration":449,"passed_time":4.926847581,"remaining_time":6.021702599},
{"learn":[0.3717457074],"iteration":450,"passed_time":4.935864052,"remaining_time":6.008402138},
{"learn":[0.3716553441],"iteration":451,"passed_time":4.945490554,"remaining_time":5.995860229},
{"learn":[0.3716186923],"iteration":452,"passed_time":4.955028344,"remaining_time":5.983224071},
{"learn":[0.3715455288],"iteration":453,"passed_time":4.964372857,"remaining_time":5.970369118},
{"learn":[0.3713506774],"iteration":454,"passed_time":4.973737432,"remaining_time":5.957553627},
{"learn":[0.3712727157],"iteration":455,"passed_time":4.982812973,"remaining_time":5.944408459},
{"learn":[0.3710672198],"iteration":456,"passed_time":4.992785747,"remaining_time":5.932347178},
{"learn":[0.370980175],"iteration":457,"passed_time":5.002360866,"remaining_time":5.919824431},
{"learn":[0.3708952615],"iteration":458,"passed_time":5.011562912,"remaining_time":5.906874805},
{"learn":[0.370860321],"iteration":459,"passed_time":5.021147262,"remaining_time":5.894390265},
{"learn":[0.3706977539],"iteration":460,"passed_time":5.031569613,"remaining_time":5.882898094},
{"learn":[0.3706098381],"iteration":461,"passed_time":5.041281396,"remaining_time":5.870583097},
{"learn":[0.3704010649],"iteration":462,"passed_time":5.051330291,"remaining_time":5.858670337},
{"learn":[0.3703030566],"iteration":463,"passed_time":5.06121163,"remaining_time":5.846572056},
{"learn":[0.3701752831],"iteration":464,"passed_time":5.072282051,"remaining_time":5.835851392},
{"learn":[0.3700462707],"iteration":465,"passed_time":5.083341807,"remaining_time":5.825117006},
{"learn":[0.3698857585],"iteration":466,"passed_time":5.093421464,"remaining_time":5.813262613},
{"learn":[0.3697235935],"iteration":467,"passed_time":5.104112201,"remaining_time":5.802110451},
{"learn":[0.3696340383],"iteration":468,"passed_time":5.113788279,"remaining_time":5.789811462},
{"learn":[0.369446417],"iteration":469,"passed_time":5.124017427,"remaining_time":5.778147311},
{"learn":[0.3693267508],"iteration":470,"passed_time":5.134547397,"remaining_time":5.766827119},
{"learn":[0.3691531482],"iteration":471,"passed_time":5.1449891,"remaining_time":5.755411536},
{"learn":[0.3690420321],"iteration":472,"passed_time":5.154798007,"remaining_time":5.743295031},
{"learn":[0.3689097359],"iteration":473,"passed_time":5.164818858,"remaining_time":5.731423459},
{"learn":[0.3687248457],"iteration":474,"passed_time":5.175194632,"remaining_time":5.719951961},
{"learn":[0.3685203244],"iteration":475,"passed_time":5.185659485,"remaining_time":5.70858313},
{"learn":[0.368457924],"iteration":476,"passed_time":5.196038493,"remaining_time":5.697123967},
{"learn":[0.368332901],"iteration":477,"passed_time":5.206983557,"remaining_time":5.686287483},
{"learn":[0.3681293125],"iteration":478,"passed_time":5.21794752,"remaining_time":5.675471102},
{"learn":[0.3679925351],"iteration":479,"passed_time":5.228439643,"remaining_time":5.664142946},
{"learn":[0.3678373102],"iteration":480,"passed_time":5.23895562,"remaining_time":5.652844005},
{"learn":[0.3676637745],"iteration":481,"passed_time":5.24980788,"remaining_time":5.641909713},
{"learn":[0.3674317859],"iteration":482,"passed_time":5.260552559,"remaining_time":5.630860607},
{"learn":[0.3673062275],"iteration":483,"passed_time":5.270982623,"remaining_time":5.619477342},
{"learn":[0.3672111198],"iteration":484,"passed_time":5.281357111,"remaining_time":5.608038994},
{"learn":[0.3670689239],"iteration":485,"passed_time":5.291046151,"remaining_time":5.595880085},
{"learn":[0.3668906497],"iteration":486,"passed_time":5.301548343,"remaining_time":5.584587885},
{"learn":[0.3667793537],"iteration":487,"passed_time":5.311669445,"remaining_time":5.57289909},
{"learn":[0.3666517809],"iteration":488,"passed_time":5.322188857,"remaining_time":5.561632936},
{"learn":[0.3665128358],"iteration":489,"passed_time":5.332904197,"remaining_time":5.550573756},
{"learn":[0.3663537544],"iteration":490,"passed_time":5.343909699,"remaining_time":5.539816775},
{"learn":[0.3661958147],"iteration":491,"passed_time":5.354491634,"remaining_time":5.528621443},
{"learn":[0.3660771897],"iteration":492,"passed_time":5.364648504,"remaining_time":5.516991463},
{"learn":[0.3658866328],"iteration":493,"passed_time":5.374903556,"remaining_time":5.505468015},
{"learn":[0.3657858969],"iteration":494,"passed_time":5.385353017,"remaining_time":5.494148027},
{"learn":[0.3656863314],"iteration":495,"passed_time":5.395401886,"remaining_time":5.482424498},
{"learn":[0.3655414658],"iteration":496,"passed_time":5.405183797,"remaining_time":5.470437525},
{"learn":[0.3654209674],"iteration":497,"passed_time":5.414979576,"remaining_time":5.458473388},
{"learn":[0.3652601588],"iteration":498,"passed_time":5.425028188,"remaining_time":5.446771788},
{"learn":[0.3651578217],"iteration":499,"passed_time":5.434997029,"remaining_time":5.434997029},
{"learn":[0.3650266611],"iteration":500,"passed_time":5.44558516,"remaining_time":5.423846297},
{"learn":[0.3648797448],"iteration":501,"passed_time":5.45593077,"remaining_time":5.412457219},
{"learn":[0.3647397754],"iteration":502,"passed_time":5.465814173,"remaining_time":5.400615595},
{"learn":[0.3645362211],"iteration":503,"passed_time":5.47630565,"remaining_time":5.389380164},
{"learn":[0.3644037277],"iteration":504,"passed_time":5.486320621,"remaining_time":5.377680609},
{"learn":[0.364237306],"iteration":505,"passed_time":5.49589398,"remaining_time":5.365556574},
{"learn":[0.3641607238],"iteration":506,"passed_time":5.505861808,"remaining_time":5.353826177},
{"learn":[0.3640168182],"iteration":507,"passed_time":5.515719314,"remaining_time":5.341995871},
{"learn":[0.3639424626],"iteration":508,"passed_time":5.526275053,"remaining_time":5.330846859},
{"learn":[0.3638121444],"iteration":509,"passed_time":5.536525892,"remaining_time":5.31940723},
{"learn":[0.3636739443],"iteration":510,"passed_time":5.547174194,"remaining_time":5.308352604},
{"learn":[0.3635666532],"iteration":511,"passed_time":5.55790882,"remaining_time":5.297381844},
{"learn":[0.3634746866],"iteration":512,"passed_time":5.568377174,"remaining_time":5.286159228},
{"learn":[0.3632993068],"iteration":513,"passed_time":5.57994634,"remaining_time":5.275980392},
{"learn":[0.3631599019],"iteration":514,"passed_time":5.590916923,"remaining_time":5.265232442},
{"learn":[0.3630843392],"iteration":515,"passed_time":5.602200672,"remaining_time":5.254777374},
{"learn":[0.3629797399],"iteration":516,"passed_time":5.613503257,"remaining_time":5.244336699},
{"learn":[0.3628582683],"iteration":517,"passed_time":5.624406206,"remaining_time":5.233520833},
{"learn":[0.3626932241],"iteration":518,"passed_time":5.635514932,"remaining_time":5.222895341},
{"learn":[0.3625478094],"iteration":519,"passed_time":5.646826018,"remaining_time":5.212454786},
{"learn":[0.3624377147],"iteration":520,"passed_time":5.658903388,"remaining_time":5.202715399},
{"learn":[0.3623149681],"iteration":521,"passed_time":5.671618958,"remaining_time":5.19355146},
{"learn":[0.3621580746],"iteration":522,"passed_time":5.683235891,"remaining_time":5.183371932},
{"learn":[0.3620939613],"iteration":523,"passed_time":5.694810528,"remaining_time":5.173148495},
{"learn":[0.3620012785],"iteration":524,"passed_time":5.706251771,"remaining_time":5.162799221},
{"learn":[0.3619073425],"iteration":525,"passed_time":5.717296548,"remaining_time":5.152088525},
{"learn":[0.361746952],"iteration":526,"passed_time":5.73020777,"remaining_time":5.143051755},
{"learn":[0.3616487996],"iteration":527,"passed_time":5.742334457,"remaining_time":5.133298984},
{"learn":[0.3615609285],"iteration":528,"passed_time":5.754230219,"remaining_time":5.123331631},
{"learn":[0.3614808686],"iteration":529,"passed_time":5.765587768,"remaining_time":5.112879718},
{"learn":[0.3613356969],"iteration":530,"passed_time":5.777819917,"remaining_time":5.103196876},
{"learn":[0.3612119691],"iteration":531,"passed_time":5.789873765,"remaining_time":5.093347598},
{"learn":[0.3610908152],"iteration":532,"passed_time":5.802011631,"remaining_time":5.083563661},
{"learn":[0.3609991367],"iteration":533,"passed_time":5.812361709,"remaining_time":5.07221078},
{"learn":[0.360926342],"iteration":534,"passed_time":5.822449692,"remaining_time":5.060633844},
{"learn":[0.3608031837],"iteration":535,"passed_time":5.834120192,"remaining_time":5.050432405},
{"learn":[0.360709998],"iteration":536,"passed_time":5.846640601,"remaining_time":5.040958284},
{"learn":[0.3605992739],"iteration":537,"passed_time":5.859976762,"remaining_time":5.032173353},
{"learn":[0.360467432],"iteration":538,"passed_time":5.872686288,"remaining_time":5.022835582},
{"learn":[0.360399392],"iteration":539,"passed_time":5.884077821,"remaining_time":5.012362588},
{"learn":[0.360250487],"iteration":540,"passed_time":5.895472639,"remaining_time":5.001888986},
{"learn":[0.3601370215],"iteration":541,"passed_time":5.9061863,"remaining_time":4.990836394},
{"learn":[0.3599534772],"iteration":542,"passed_time":5.916059137,"remaining_time":4.979077396},
{"learn":[0.3597918346],"iteration":543,"passed_time":5.926820774,"remaining_time":4.968070354},
{"learn":[0.3596579389],"iteration":544,"passed_time":5.93771511,"remaining_time":4.957175},
{"learn":[0.3594272626],"iteration":545,"passed_time":5.948087372,"remaining_time":4.945845544},
{"learn":[0.3593178246],"iteration":546,"passed_time":5.958501425,"remaining_time":4.934554197},
{"learn":[0.3591920089],"iteration":547,"passed_time":5.96872453,"remaining_time":4.923108554},
{"learn":[0.3589888002],"iteration":548,"passed_time":5.978594515,"remaining_time":4.911377279},
{"learn":[0.3588591022],"iteration":549,"passed_time":5.988682979,"remaining_time":4.899831528},
{"learn":[0.3587833817],"iteration":550,"passed_time":5.997577333,"remaining_time":4.887318008},
{"learn":[0.3586969687],"iteration":551,"passed_time":6.007281009,"remaining_time":4.875474442},
{"learn":[0.3586011287],"iteration":552,"passed_time":6.016423405,"remaining_time":4.863184922},
{"learn":[0.3584448964],"iteration":553,"passed_time":6.025576653,"remaining_time":4.8509155},
{"learn":[0.3583626723],"iteration":554,"passed_time":6.035382543,"remaining_time":4.839180597},
{"learn":[0.3582468294],"iteration":555,"passed_time":6.045021149,"remaining_time":4.827319047},
{"learn":[0.3581329319],"iteration":556,"passed_time":6.054560051,"remaining_time":4.815386181},
{"learn":[0.3580130486],"iteration":557,"passed_time":6.064223426,"remaining_time":4.803560492},
{"learn":[0.3578887587],"iteration":558,"passed_time":6.073901243,"remaining_time":4.791753932},
{"learn":[0.3577919028],"iteration":559,"passed_time":6.083553695,"remaining_time":4.779935046},
{"learn":[0.357611078],"iteration":560,"passed_time":6.093403689,"remaining_time":4.768278466},
{"learn":[0.3574863477],"iteration":561,"passed_time":6.103240559,"remaining_time":4.756618087},
{"learn":[0.357395869],"iteration":562,"passed_time":6.112879383,"remaining_time":4.744810462},
{"learn":[0.3572706788],"iteration":563,"passed_time":6.123332509,"remaining_time":4.733640025},
{"learn":[0.3571148884],"iteration":564,"passed_time":6.13415145,"remaining_time":4.722753771},
{"learn":[0.3570006234],"iteration":565,"passed_time":6.144122569,"remaining_time":4.711217659},
{"learn":[0.3568863773],"iteration":566,"passed_time":6.15429497,"remaining_time":4.69984078},
{"learn":[0.3566965064],"iteration":567,"passed_time":6.164668697,"remaining_time":4.688621262},
{"learn":[0.3565645352],"iteration":568,"passed_time":6.174828367,"remaining_time":4.677242577},
{"learn":[0.3564237438],"iteration":569,"passed_time":6.18502052,"remaining_time":4.665892673},
{"learn":[0.3563118827],"iteration":570,"passed_time":6.194999834,"remaining_time":4.654386915},
{"learn":[0.3562022388],"iteration":571,"passed_time":6.204240042,"remaining_time":4.642333458},
{"learn":[0.355994759],"iteration":572,"passed_time":6.214457224,"remaining_time":4.631017861},
{"learn":[0.3558880273],"iteration":573,"passed_time":6.223435865,"remaining_time":4.618786897},
{"learn":[0.3557808736],"iteration":574,"passed_time":6.233011087,"remaining_time":4.607008195},
{"learn":[0.3556438446],"iteration":575,"passed_time":6.242189544,"remaining_time":4.594945081},
{"learn":[0.3555512172],"iteration":576,"passed_time":6.252925071,"remaining_time":4.584033458},
{"learn":[0.3553780225],"iteration":577,"passed_time":6.263204509,"remaining_time":4.572789451},
{"learn":[0.3552562952],"iteration":578,"passed_time":6.273079525,"remaining_time":4.561254715},
{"learn":[0.3551247978],"iteration":579,"passed_time":6.283125285,"remaining_time":4.549849344},
{"learn":[0.3549876519],"iteration":580,"passed_time":6.292948523,"remaining_time":4.538288178},
{"learn":[0.3549192848],"iteration":581,"passed_time":6.302200709,"remaining_time":4.526322846},
{"learn":[0.354793261],"iteration":582,"passed_time":6.310866424,"remaining_time":4.513947339},
{"learn":[0.354635856],"iteration":583,"passed_time":6.320563509,"remaining_time":4.502319212},
{"learn":[0.3545035294],"iteration":584,"passed_time":6.330773044,"remaining_time":4.491061219},
{"learn":[0.3543630537],"iteration":585,"passed_time":6.341318965,"remaining_time":4.480044457},
{"learn":[0.3542299578],"iteration":586,"passed_time":6.351809129,"remaining_time":4.468990069},
{"learn":[0.3540816243],"iteration":587,"passed_time":6.361944411,"remaining_time":4.457688941},
{"learn":[0.3538707346],"iteration":588,"passed_time":6.372465963,"remaining_time":4.446661309},
{"learn":[0.3537793093],"iteration":589,"passed_time":6.382308637,"remaining_time":4.435163629},
{"learn":[0.3537459323],"iteration":590,"passed_time":6.391787286,"remaining_time":4.423419628},
{"learn":[0.3535994957],"iteration":591,"passed_time":6.401390298,"remaining_time":4.411768989},
{"learn":[0.3535309616],"iteration":592,"passed_time":6.410990187,"remaining_time":4.400123113},
{"learn":[0.3534514191],"iteration":593,"passed_time":6.421024973,"remaining_time":4.388781379},
{"learn":[0.3533032587],"iteration":594,"passed_time":6.430376038,"remaining_time":4.376978647},
{"learn":[0.35321792],"iteration":595,"passed_time":6.440541087,"remaining_time":4.365735905},
{"learn":[0.3531524683],"iteration":596,"passed_time":6.450006245,"remaining_time":4.354024316},
{"learn":[0.3530047265],"iteration":597,"passed_time":6.459758838,"remaining_time":4.342513466},
{"learn":[0.3528220856],"iteration":598,"passed_time":6.470058242,"remaining_time":4.331374549},
{"learn":[0.3527723348],"iteration":599,"passed_time":6.479838341,"remaining_time":4.319892228},
{"learn":[0.3526014942],"iteration":600,"passed_time":6.489915467,"remaining_time":4.308612764},
{"learn":[0.3525256533],"iteration":601,"passed_time":6.499637682,"remaining_time":4.297102654},
{"learn":[0.352371322],"iteration":602,"passed_time":6.509606782,"remaining_time":4.285761016},
{"learn":[0.3523149264],"iteration":603,"passed_time":6.519367176,"remaining_time":4.274287089},
{"learn":[0.3522559756],"iteration":604,"passed_time":6.528552119,"remaining_time":4.262443119},
{"learn":[0.3521983792],"iteration":605,"passed_time":6.538401275,"remaining_time":4.251039773},
{"learn":[0.3520979149],"iteration":606,"passed_time":6.549295856,"remaining_time":4.240318404},
{"learn":[0.3519631612],"iteration":607,"passed_time":6.559477858,"remaining_time":4.22913704},
{"learn":[0.3518087876],"iteration":608,"passed_time":6.570093575,"remaining_time":4.218237418},
{"learn":[0.3516578532],"iteration":609,"passed_time":6.580663698,"remaining_time":4.207309577},
{"learn":[0.3515702684],"iteration":610,"passed_time":6.590360043,"remaining_time":4.195826607},
{"learn":[0.3514467664],"iteration":611,"passed_time":6.600270795,"remaining_time":4.184485406},
{"learn":[0.3513513018],"iteration":612,"passed_time":6.609951189,"remaining_time":4.173003442},
{"learn":[0.3512079571],"iteration":613,"passed_time":6.620335152,"remaining_time":4.161969656},
{"learn":[0.3511324623],"iteration":614,"passed_time":6.630677919,"remaining_time":4.150912193},
{"learn":[0.3509978432],"iteration":615,"passed_time":6.641006471,"remaining_time":4.139848189},
{"learn":[0.3508781688],"iteration":616,"passed_time":6.651740345,"remaining_time":4.129038172},
{"learn":[0.3507130788],"iteration":617,"passed_time":6.661977201,"remaining_time":4.117921183},
{"learn":[0.3505995578],"iteration":618,"passed_time":6.672407057,"remaining_time":4.10692583},
{"learn":[0.3504972482],"iteration":619,"passed_time":6.682372728,"remaining_time":4.095647801},
{"learn":[0.3504250516],"iteration":620,"passed_time":6.692520031,"remaining_time":4.08448485},
{"learn":[0.3503153769],"iteration":621,"passed_time":6.702259391,"remaining_time":4.073077251},
{"learn":[0.3502889228],"iteration":622,"passed_time":6.712556924,"remaining_time":4.062012778},
{"learn":[0.3501284407],"iteration":623,"passed_time":6.722766529,"remaining_time":4.05089778},
{"learn":[0.3500984302],"iteration":624,"passed_time":6.732799597,"remaining_time":4.039679758},
{"learn":[0.3500639033],"iteration":625,"passed_time":6.74229502,"remaining_time":4.028144309},
{"learn":[0.349910384],"iteration":626,"passed_time":6.752804456,"remaining_time":4.0172186},
{"learn":[0.3498050077],"iteration":627,"passed_time":6.763253579,"remaining_time":4.006258489},
{"learn":[0.3496511663],"iteration":628,"passed_time":6.773687658,"remaining_time":3.99529113},
{"learn":[0.3495180126],"iteration":629,"passed_time":6.784181546,"remaining_time":3.984360591},
{"learn":[0.3493333341],"iteration":630,"passed_time":6.795009746,"remaining_time":3.973626935},
{"learn":[0.3492015043],"iteration":631,"passed_time":6.804951327,"remaining_time":3.962376722},
{"learn":[0.3491247939],"iteration":632,"passed_time":6.814998253,"remaining_time":3.95119172},
{"learn":[0.3489411796],"iteration":633,"passed_time":6.824871358,"remaining_time":3.939909964},
{"learn":[0.348843747],"iteration":634,"passed_time":6.834711253,"remaining_time":3.928613555},
{"learn":[0.348751862],"iteration":635,"passed_time":6.844501487,"remaining_time":3.917293304},
{"learn":[0.3486587517],"iteration":636,"passed_time":6.854292383,"remaining_time":3.905978234},
{"learn":[0.348527412],"iteration":637,"passed_time":6.864176799,"remaining_time":3.894721005},
{"learn":[0.3484321951],"iteration":638,"passed_time":6.873967947,"remaining_time":3.883415381},
{"learn":[0.3483648026],"iteration":639,"passed_time":6.884117852,"remaining_time":3.872316292},
{"learn":[0.3482967481],"iteration":640,"passed_time":6.893973175,"remaining_time":3.861055179},
{"learn":[0.348188907],"iteration":641,"passed_time":6.903668265,"remaining_time":3.849709095},
{"learn":[0.3480931437],"iteration":642,"passed_time":6.913760801,"remaining_time":3.838588812},
{"learn":[0.3479530401],"iteration":643,"passed_time":6.923953617,"remaining_time":3.827527155},
{"learn":[0.3478486077],"iteration":644,"passed_time":6.933734927,"remaining_time":3.816241704},
{"learn":[0.3477018156],"iteration":645,"passed_time":6.943611652,"remaining_time":3.805013196},
{"learn":[0.3475888616],"iteration":646,"passed_time":6.953626222,"remaining_time":3.793864075},
{"learn":[0.3474849112],"iteration":647,"passed_time":6.962852357,"remaining_time":3.782290169},
{"learn":[0.3473823172],"iteration":648,"passed_time":6.97237175,"remaining_time":3.770882102},
{"learn":[0.3473152084],"iteration":649,"passed_time":6.981876386,"remaining_time":3.7594719},
{"learn":[0.3472293722],"iteration":650,"passed_time":6.991730315,"remaining_time":3.748254808},
{"learn":[0.3471319538],"iteration":651,"passed_time":7.001495943,"remaining_time":3.736994767},
{"learn":[0.3469936253],"iteration":652,"passed_time":7.011327215,"remaining_time":3.725774186},
{"learn":[0.3468697126],"iteration":653,"passed_time":7.021270813,"remaining_time":3.71461728},
{"learn":[0.3467265532],"iteration":654,"passed_time":7.030923192,"remaining_time":3.703310689},
{"learn":[0.3466547307],"iteration":655,"passed_time":7.041024886,"remaining_time":3.692244757},
{"learn":[0.3465534448],"iteration":656,"passed_time":7.051410649,"remaining_time":3.681330065},
{"learn":[0.3464697123],"iteration":657,"passed_time":7.061749138,"remaining_time":3.670392409},
{"learn":[0.3463302155],"iteration":658,"passed_time":7.073169603,"remaining_time":3.660016441},
{"learn":[0.3462998181],"iteration":659,"passed_time":7.083196123,"remaining_time":3.648919215},
{"learn":[0.3461643267],"iteration":660,"passed_time":7.093352996,"remaining_time":3.637892081},
{"learn":[0.3460653129],"iteration":661,"passed_time":7.10367157,"remaining_time":3.626950137},
{"learn":[0.3459913426],"iteration":662,"passed_time":7.11320133,"remaining_time":3.615609122},
{"learn":[0.3458250489],"iteration":663,"passed_time":7.123691033,"remaining_time":3.604759318},
{"learn":[0.3457500726],"iteration":664,"passed_time":7.133633675,"remaining_time":3.593635009},
{"learn":[0.345661893],"iteration":665,"passed_time":7.144060125,"remaining_time":3.58275688},
{"learn":[0.3455831663],"iteration":666,"passed_time":7.154221569,"remaining_time":3.5717478},
{"learn":[0.3454785596],"iteration":667,"passed_time":7.164611845,"remaining_time":3.560854989},
{"learn":[0.3452617522],"iteration":668,"passed_time":7.174573475,"remaining_time":3.5497516},
{"learn":[0.3450918411],"iteration":669,"passed_time":7.184891598,"remaining_time":3.538827205},
{"learn":[0.3449643657],"iteration":670,"passed_time":7.195168803,"remaining_time":3.527884555},
{"learn":[0.3447963404],"iteration":671,"passed_time":7.204995326,"remaining_time":3.516723909},
{"learn":[0.3446839649],"iteration":672,"passed_time":7.215528712,"remaining_time":3.505910682},
{"learn":[0.3445693905],"iteration":673,"passed_time":7.22609015,"remaining_time":3.495111853},
{"learn":[0.3444476836],"iteration":674,"passed_time":7.236365962,"remaining_time":3.484176204},
{"learn":[0.3444133499],"iteration":675,"passed_time":7.24634239,"remaining_time":3.473099015},
{"learn":[0.344313055],"iteration":676,"passed_time":7.256772005,"remaining_time":3.462241296},
{"learn":[0.3442022583],"iteration":677,"passed_time":7.267103969,"remaining_time":3.451338463},
{"learn":[0.3440368161],"iteration":678,"passed_time":7.277289878,"remaining_time":3.440368263},
{"learn":[0.3439123575],"iteration":679,"passed_time":7.287782611,"remaining_time":3.429544758},
{"learn":[0.3438107787],"iteration":680,"passed_time":7.297833712,"remaining_time":3.418515351},
{"learn":[0.3437450927],"iteration":681,"passed_time":7.307457209,"remaining_time":3.407289432},
{"learn":[0.3436273202],"iteration":682,"passed_time":7.317743746,"remaining_time":3.396375941},
{"learn":[0.3434608859],"iteration":683,"passed_time":7.328412328,"remaining_time":3.385640783},
{"learn":[0.3433811239],"iteration":684,"passed_time":7.337963922,"remaining_time":3.374392169},
{"learn":[0.3432561982],"iteration":685,"passed_time":7.348172505,"remaining_time":3.363449222},
{"learn":[0.3431271665],"iteration":686,"passed_time":7.358280754,"remaining_time":3.352462702},
{"learn":[0.3429858069],"iteration":687,"passed_time":7.368298747,"remaining_time":3.341437804},
{"learn":[0.3429046809],"iteration":688,"passed_time":7.378097877,"remaining_time":3.330317039},
{"learn":[0.34277554],"iteration":689,"passed_time":7.387737564,"remaining_time":3.319128471},
{"learn":[0.3426537812],"iteration":690,"passed_time":7.397746909,"remaining_time":3.308109689},
{"learn":[0.3425439199],"iteration":691,"passed_time":7.407240986,"remaining_time":3.296864485},
{"learn":[0.3424862927],"iteration":692,"passed_time":7.417087242,"remaining_time":3.285780351},
{"learn":[0.3424357007],"iteration":693,"passed_time":7.427056206,"remaining_time":3.274753889},
{"learn":[0.3423092072],"iteration":694,"passed_time":7.437132187,"remaining_time":3.263777435},
{"learn":[0.3422017421],"iteration":695,"passed_time":7.447038169,"remaining_time":3.252729315},
{"learn":[0.3420810115],"iteration":696,"passed_time":7.45696254,"remaining_time":3.241692467},
{"learn":[0.3419700612],"iteration":697,"passed_time":7.46685111,"remaining_time":3.230643317},
{"learn":[0.3418932637],"iteration":698,"passed_time":7.476969984,"remaining_time":3.21969666},
{"learn":[0.3418602098],"iteration":699,"passed_time":7.486183028,"remaining_time":3.208364155},
{"learn":[0.3417145581],"iteration":700,"passed_time":7.496433778,"remaining_time":3.197480313},
{"learn":[0.3415586441],"iteration":701,"passed_time":7.506059643,"remaining_time":3.186333011},
{"learn":[0.3414936823],"iteration":702,"passed_time":7.515582155,"remaining_time":3.175146373},
{"learn":[0.3413242576],"iteration":703,"passed_time":7.526360606,"remaining_time":3.164492527},
{"learn":[0.3412767905],"iteration":704,"passed_time":7.536332504,"remaining_time":3.153500835},
{"learn":[0.3412294075],"iteration":705,"passed_time":7.546026879,"remaining_time":3.142396463},
{"learn":[0.3411259669],"iteration":706,"passed_time":7.556138454,"remaining_time":3.131468978},
{"learn":[0.3410311984],"iteration":707,"passed_time":7.566336113,"remaining_time":3.120579301},
{"learn":[0.3409542607],"iteration":708,"passed_time":7.576038285,"remaining_time":3.10948821},
{"learn":[0.3408481097],"iteration":709,"passed_time":7.586840386,"remaining_time":3.098850299},
{"learn":[0.3406855431],"iteration":710,"passed_time":7.597414196,"remaining_time":3.088119132},
{"learn":[0.3405753259],"iteration":711,"passed_time":7.608870481,"remaining_time":3.077745363},
{"learn":[0.3403808381],"iteration":712,"passed_time":7.62072735,"remaining_time":3.067529803},
{"learn":[0.3401278832],"iteration":713,"passed_time":7.632685825,"remaining_time":3.057350344},
{"learn":[0.3400160665],"iteration":714,"passed_time":7.644372599,"remaining_time":3.04705761},
{"learn":[0.3398976612],"iteration":715,"passed_time":7.656123948,"remaining_time":3.036786594},
{"learn":[0.3397798833],"iteration":716,"passed_time":7.667677148,"remaining_time":3.02643324},
{"learn":[0.3396332868],"iteration":717,"passed_time":7.679203241,"remaining_time":3.016065897},
{"learn":[0.3395336123],"iteration":718,"passed_time":7.690401956,"remaining_time":3.005567385},
{"learn":[0.3394420666],"iteration":719,"passed_time":7.702084162,"remaining_time":2.995254952},
{"learn":[0.3393261578],"iteration":720,"passed_time":7.713918013,"remaining_time":2.984997401},
{"learn":[0.3392315373],"iteration":721,"passed_time":7.724703627,"remaining_time":2.974331867},
{"learn":[0.339122015],"iteration":722,"passed_time":7.735435264,"remaining_time":2.963645322},
{"learn":[0.3389873176],"iteration":723,"passed_time":7.745940829,"remaining_time":2.952872471},
{"learn":[0.3389271755],"iteration":724,"passed_time":7.756796845,"remaining_time":2.942233286},
{"learn":[0.3388389724],"iteration":725,"passed_time":7.768078855,"remaining_time":2.931754279},
{"learn":[0.3387163876],"iteration":726,"passed_time":7.779284286,"remaining_time":2.921244305},
{"learn":[0.3385656172],"iteration":727,"passed_time":7.790936232,"remaining_time":2.910899251},
{"learn":[0.3384932369],"iteration":728,"passed_time":7.80173332,"remaining_time":2.900232826},
{"learn":[0.3383945943],"iteration":729,"passed_time":7.813717356,"remaining_time":2.890005049},
{"learn":[0.3381506934],"iteration":730,"passed_time":7.825884313,"remaining_time":2.879839782},
{"learn":[0.3380109512],"iteration":731,"passed_time":7.836600628,"remaining_time":2.869137935},
{"learn":[0.3379233056],"iteration":732,"passed_time":7.846922766,"remaining_time":2.858292467},
{"learn":[0.3378181443],"iteration":733,"passed_time":7.857349601,"remaining_time":2.847486368},
{"learn":[0.3376658246],"iteration":734,"passed_time":7.867425998,"remaining_time":2.836554952},
{"learn":[0.3375100676],"iteration":735,"passed_time":7.877186604,"remaining_time":2.825512586},
{"learn":[0.3373472206],"iteration":736,"passed_time":7.886865933,"remaining_time":2.814444695},
{"learn":[0.3371665083],"iteration":737,"passed_time":7.896515529,"remaining_time":2.803370012},
{"learn":[0.337008392],"iteration":738,"passed_time":7.906159156,"remaining_time":2.792297077},
{"learn":[0.3369229489],"iteration":739,"passed_time":7.916195259,"remaining_time":2.781365902},
{"learn":[0.3368102894],"iteration":740,"passed_time":7.926389804,"remaining_time":2.770492522},
{"learn":[0.3367627775],"iteration":741,"passed_time":7.936912121,"remaining_time":2.759734942},
{"learn":[0.3366114595],"iteration":742,"passed_time":7.948179696,"remaining_time":2.749235777},
{"learn":[0.336556836],"iteration":743,"passed_time":7.958378606,"remaining_time":2.738366832},
{"learn":[0.336412578],"iteration":744,"passed_time":7.969714363,"remaining_time":2.727888809},
{"learn":[0.3362770204],"iteration":745,"passed_time":7.980654043,"remaining_time":2.717273629},
{"learn":[0.3361673793],"iteration":746,"passed_time":7.991580033,"remaining_time":2.706652943},
{"learn":[0.3360876082],"iteration":747,"passed_time":8.002765478,"remaining_time":2.696118851},
{"learn":[0.3359070666],"iteration":748,"passed_time":8.013973777,"remaining_time":2.685590678},
{"learn":[0.3357958668],"iteration":749,"passed_time":8.024888463,"remaining_time":2.674962821},
{"learn":[0.3357211314],"iteration":750,"passed_time":8.035828056,"remaining_time":2.664342458},
{"learn":[0.3355771555],"iteration":751,"passed_time":8.048046988,"remaining_time":2.654143156},
{"learn":[0.3355260186],"iteration":752,"passed_time":8.059780358,"remaining_time":2.643779214},
{"learn":[0.3354156324],"iteration":753,"passed_time":8.071644711,"remaining_time":2.633454375},
{"learn":[0.3352635478],"iteration":754,"passed_time":8.083937196,"remaining_time":2.623264388},
{"learn":[0.3351454953],"iteration":755,"passed_time":8.095946668,"remaining_time":2.612977496},
{"learn":[0.3350300843],"iteration":756,"passed_time":8.108669125,"remaining_time":2.602914924},
{"learn":[0.3349033303],"iteration":757,"passed_time":8.12089626,"remaining_time":2.592687196},
{"learn":[0.3348286527],"iteration":758,"passed_time":8.132262261,"remaining_time":2.582180771},
{"learn":[0.334697483],"iteration":759,"passed_time":8.143387597,"remaining_time":2.571596083},
{"learn":[0.3346380014],"iteration":760,"passed_time":8.153455866,"remaining_time":2.560677992},
{"learn":[0.3345101224],"iteration":761,"passed_time":8.163578867,"remaining_time":2.549779226},
{"learn":[0.3344074286],"iteration":762,"passed_time":8.173406401,"remaining_time":2.538790717},
{"learn":[0.3342761674],"iteration":763,"passed_time":8.183175809,"remaining_time":2.527787292},
{"learn":[0.3342070761],"iteration":764,"passed_time":8.194211244,"remaining_time":2.517176003},
{"learn":[0.3341132132],"iteration":765,"passed_time":8.204702795,"remaining_time":2.50639746},
{"learn":[0.3339807849],"iteration":766,"passed_time":8.215703859,"remaining_time":2.495774445},
{"learn":[0.3339069836],"iteration":767,"passed_time":8.225438126,"remaining_time":2.484767767},
{"learn":[0.3337628184],"iteration":768,"passed_time":8.235126044,"remaining_time":2.473750476},
{"learn":[0.3336447199],"iteration":769,"passed_time":8.24485562,"remaining_time":2.462749081},
{"learn":[0.3335409387],"iteration":770,"passed_time":8.254302803,"remaining_time":2.45166711},
{"learn":[0.3334263089],"iteration":771,"passed_time":8.264257511,"remaining_time":2.440739265},
{"learn":[0.3332975245],"iteration":772,"passed_time":8.27445634,"remaining_time":2.429885626},
{"learn":[0.3332722214],"iteration":773,"passed_time":8.284870617,"remaining_time":2.419096589},
{"learn":[0.3331579218],"iteration":774,"passed_time":8.295503917,"remaining_time":2.408372105},
{"learn":[0.3330961904],"iteration":775,"passed_time":8.306100986,"remaining_time":2.397637398},
{"learn":[0.3330193375],"iteration":776,"passed_time":8.316725564,"remaining_time":2.38691094},
{"learn":[0.332943875],"iteration":777,"passed_time":8.327015362,"remaining_time":2.376089216},
{"learn":[0.3328609544],"iteration":778,"passed_time":8.336940549,"remaining_time":2.365165419},
{"learn":[0.3327592759],"iteration":779,"passed_time":8.346547751,"remaining_time":2.354154494},
{"learn":[0.3326741842],"iteration":780,"passed_time":8.357366716,"remaining_time":2.343486954},
{"learn":[0.3326112714],"iteration":781,"passed_time":8.36700805,"remaining_time":2.332490735},
{"learn":[0.3324831988],"iteration":782,"passed_time":8.376672944,"remaining_time":2.321504507},
{"learn":[0.3323089129],"iteration":783,"passed_time":8.386521052,"remaining_time":2.310572127},
{"learn":[0.3321997451],"iteration":784,"passed_time":8.396480827,"remaining_time":2.299673093},
{"learn":[0.3320992953],"iteration":785,"passed_time":8.406501275,"remaining_time":2.288792968},
{"learn":[0.3319435524],"iteration":786,"passed_time":8.416494851,"remaining_time":2.277907755},
{"learn":[0.3318436393],"iteration":787,"passed_time":8.426496748,"remaining_time":2.267027044},
{"learn":[0.3316538032],"iteration":788,"passed_time":8.436627835,"remaining_time":2.256183109},
{"learn":[0.3315294073],"iteration":789,"passed_time":8.446760067,"remaining_time":2.245341284},
{"learn":[0.3314653439],"iteration":790,"passed_time":8.456521285,"remaining_time":2.234403222},
{"learn":[0.3312954778],"iteration":791,"passed_time":8.466303558,"remaining_time":2.223473662},
{"learn":[0.3311795903],"iteration":792,"passed_time":8.47618255,"remaining_time":2.212572242},
{"learn":[0.3311258326],"iteration":793,"passed_time":8.486080917,"remaining_time":2.201678424},
{"learn":[0.3310931353],"iteration":794,"passed_time":8.496522841,"remaining_time":2.190927274},
{"learn":[0.3309916138],"iteration":795,"passed_time":8.506513446,"remaining_time":2.180061235},
{"learn":[0.3308571044],"iteration":796,"passed_time":8.516666107,"remaining_time":2.16923867},
{"learn":[0.3307264549],"iteration":797,"passed_time":8.526877978,"remaining_time":2.158432771},
{"learn":[0.3305452472],"iteration":798,"passed_time":8.536818882,"remaining_time":2.147560194},
{"learn":[0.3304993271],"iteration":799,"passed_time":8.546750182,"remaining_time":2.136687546},
{"learn":[0.3304259332],"iteration":800,"passed_time":8.556721601,"remaining_time":2.125827214},
{"learn":[0.3303090621],"iteration":801,"passed_time":8.567190614,"remaining_time":2.115091947},
{"learn":[0.3302140624],"iteration":802,"passed_time":8.577499465,"remaining_time":2.104318051},
{"learn":[0.330145502],"iteration":803,"passed_time":8.588136378,"remaining_time":2.093625286},
{"learn":[0.3300635906],"iteration":804,"passed_time":8.597954023,"remaining_time":2.082734204},
{"learn":[0.3299497698],"iteration":805,"passed_time":8.608355146,"remaining_time":2.071986226},
{"learn":[0.3298428934],"iteration":806,"passed_time":8.619302853,"remaining_time":2.061369827},
{"learn":[0.3297467992],"iteration":807,"passed_time":8.629664,"remaining_time":2.050613228},
{"learn":[0.3296217152],"iteration":808,"passed_time":8.639826466,"remaining_time":2.039810698},
{"learn":[0.3295425462],"iteration":809,"passed_time":8.650075795,"remaining_time":2.029030125},
{"learn":[0.3293878296],"iteration":810,"passed_time":8.660437412,"remaining_time":2.018277029},
{"learn":[0.3292825829],"iteration":811,"passed_time":8.670444352,"remaining_time":2.007442781},
{"learn":[0.3292244306],"iteration":812,"passed_time":8.680754795,"remaining_time":1.996680377},
{"learn":[0.3291564357],"iteration":813,"passed_time":8.690825599,"remaining_time":1.985864326},
{"learn":[0.3290382848],"iteration":814,"passed_time":8.702958726,"remaining_time":1.975518238},
{"learn":[0.3288876108],"iteration":815,"passed_time":8.713997304,"remaining_time":1.964920961},
{"learn":[0.3287706077],"iteration":816,"passed_time":8.724126131,"remaining_time":1.954118827},
{"learn":[0.3287147648],"iteration":817,"passed_time":8.734555416,"remaining_time":1.94338519},
{"learn":[0.32863409],"iteration":818,"passed_time":8.744934318,"remaining_time":1.932641162},
{"learn":[0.3285012098],"iteration":819,"passed_time":8.755422068,"remaining_time":1.921921917},
{"learn":[0.3284213095],"iteration":820,"passed_time":8.7659904,"remaining_time":1.911220806},
{"learn":[0.3282956781],"iteration":821,"passed_time":8.77691263,"remaining_time":1.900596652},
{"learn":[0.3281587248],"iteration":822,"passed_time":8.787794597,"remaining_time":1.889963115},
{"learn":[0.3280961437],"iteration":823,"passed_time":8.798228735,"remaining_time":1.879233322},
{"learn":[0.327993704],"iteration":824,"passed_time":8.80836739,"remaining_time":1.868441568},
{"learn":[0.327844111],"iteration":825,"passed_time":8.817998321,"remaining_time":1.85754444},
{"learn":[0.3277261683],"iteration":826,"passed_time":8.827758357,"remaining_time":1.846677383},
{"learn":[0.3276864159],"iteration":827,"passed_time":8.837476512,"remaining_time":1.8358043},
{"learn":[0.3275183699],"iteration":828,"passed_time":8.847171507,"remaining_time":1.824929225},
{"learn":[0.327453442],"iteration":829,"passed_time":8.856438268,"remaining_time":1.813969284},
{"learn":[0.3273854542],"iteration":830,"passed_time":8.866498722,"remaining_time":1.80317483},
{"learn":[0.3272941099],"iteration":831,"passed_time":8.876772232,"remaining_time":1.792425162},
{"learn":[0.3271713041],"iteration":832,"passed_time":8.886487293,"remaining_time":1.781564679},
{"learn":[0.3271104734],"iteration":833,"passed_time":8.896324005,"remaining_time":1.770731157},
{"learn":[0.3269784796],"iteration":834,"passed_time":8.905812755,"remaining_time":1.759831263},
{"learn":[0.3269089311],"iteration":835,"passed_time":8.915619564,"remaining_time":1.748997139},
{"learn":[0.3268154192],"iteration":836,"passed_time":8.925793328,"remaining_time":1.738236933},
{"learn":[0.3267270794],"iteration":837,"passed_time":8.936438596,"remaining_time":1.727569275},
{"learn":[0.3266835259],"iteration":838,"passed_time":8.945485499,"remaining_time":1.716594953},
{"learn":[0.3265621065],"iteration":839,"passed_time":8.95514712,"remaining_time":1.705742309},
{"learn":[0.3264821163],"iteration":840,"passed_time":8.965102606,"remaining_time":1.694948055},
{"learn":[0.3263587951],"iteration":841,"passed_time":8.975070733,"remaining_time":1.684158166},
{"learn":[0.3262573298],"iteration":842,"passed_time":8.985016811,"remaining_time":1.67336612},
{"learn":[0.3261604698],"iteration":843,"passed_time":8.995298657,"remaining_time":1.66263814},
{"learn":[0.3260886226],"iteration":844,"passed_time":9.005663806,"remaining_time":1.651926497},
{"learn":[0.3260026041],"iteration":845,"passed_time":9.015303119,"remaining_time":1.641083546},
{"learn":[0.3259003741],"iteration":846,"passed_time":9.02523886,"remaining_time":1.630296984},
{"learn":[0.3257853252],"iteration":847,"passed_time":9.03547107,"remaining_time":1.619565569},
{"learn":[0.3256813697],"iteration":848,"passed_time":9.046794203,"remaining_time":1.609029358},
{"learn":[0.3255457084],"iteration":849,"passed_time":9.057243454,"remaining_time":1.59833708},
{"learn":[0.3254941844],"iteration":850,"passed_time":9.067855835,"remaining_time":1.587673936},
{"learn":[0.3253903087],"iteration":851,"passed_time":9.078245532,"remaining_time":1.576972229},
{"learn":[0.3252234155],"iteration":852,"passed_time":9.088659297,"remaining_time":1.566275401},
{"learn":[0.3251159339],"iteration":853,"passed_time":9.099646645,"remaining_time":1.555677295},
{"learn":[0.3249572292],"iteration":854,"passed_time":9.10989911,"remaining_time":1.54495365},
{"learn":[0.3248807726],"iteration":855,"passed_time":9.120374391,"remaining_time":1.534268589},
{"learn":[0.3247513362],"iteration":856,"passed_time":9.130869688,"remaining_time":1.523587358},
{"learn":[0.3246433084],"iteration":857,"passed_time":9.141347179,"remaining_time":1.512903612},
{"learn":[0.3245015595],"iteration":858,"passed_time":9.151632822,"remaining_time":1.502188857},
{"learn":[0.3243961801],"iteration":859,"passed_time":9.163425505,"remaining_time":1.491720431},
{"learn":[0.3242811279],"iteration":860,"passed_time":9.173576712,"remaining_time":1.480983929},
{"learn":[0.3242373837],"iteration":861,"passed_time":9.183509272,"remaining_time":1.470213781},
{"learn":[0.3241521685],"iteration":862,"passed_time":9.194132242,"remaining_time":1.459555176},
{"learn":[0.3240686727],"iteration":863,"passed_time":9.204194864,"remaining_time":1.448808451},
{"learn":[0.3239726123],"iteration":864,"passed_time":9.214252836,"remaining_time":1.438062581},
{"learn":[0.3238658669],"iteration":865,"passed_time":9.224414858,"remaining_time":1.427334401},
{"learn":[0.3237820772],"iteration":866,"passed_time":9.235543213,"remaining_time":1.416755764},
{"learn":[0.3236676541],"iteration":867,"passed_time":9.245982537,"remaining_time":1.406071077},
{"learn":[0.3235992603],"iteration":868,"passed_time":9.257257107,"remaining_time":1.395512867},
{"learn":[0.3234806294],"iteration":869,"passed_time":9.267662209,"remaining_time":1.384823089},
{"learn":[0.3233922628],"iteration":870,"passed_time":9.278150531,"remaining_time":1.37414629},
{"learn":[0.3233051832],"iteration":871,"passed_time":9.288093078,"remaining_time":1.36338981},
{"learn":[0.3231135662],"iteration":872,"passed_time":9.299128644,"remaining_time":1.352794201},
{"learn":[0.3230379854],"iteration":873,"passed_time":9.309032708,"remaining_time":1.342034464},
{"learn":[0.3228697246],"iteration":874,"passed_time":9.319477024,"remaining_time":1.331353861},
{"learn":[0.3228102472],"iteration":875,"passed_time":9.329476153,"remaining_time":1.32061078},
{"learn":[0.3226903441],"iteration":876,"passed_time":9.339677445,"remaining_time":1.309897749},
{"learn":[0.3226309076],"iteration":877,"passed_time":9.349302895,"remaining_time":1.299105869},
{"learn":[0.3225707136],"iteration":878,"passed_time":9.358898584,"remaining_time":1.288312547},
{"learn":[0.322458108],"iteration":879,"passed_time":9.368599985,"remaining_time":1.277536362},
{"learn":[0.3222669859],"iteration":880,"passed_time":9.378122269,"remaining_time":1.266738422},
{"learn":[0.3221651772],"iteration":881,"passed_time":9.387674475,"remaining_time":1.255947379},
{"learn":[0.3220718017],"iteration":882,"passed_time":9.397487049,"remaining_time":1.245193641},
{"learn":[0.3219479797],"iteration":883,"passed_time":9.407838379,"remaining_time":1.234512728},
{"learn":[0.3218738309],"iteration":884,"passed_time":9.417801952,"remaining_time":1.223782175},
{"learn":[0.3217314998],"iteration":885,"passed_time":9.427840396,"remaining_time":1.213062986},
{"learn":[0.3215923677],"iteration":886,"passed_time":9.438142741,"remaining_time":1.202378951},
{"learn":[0.3215119461],"iteration":887,"passed_time":9.448170995,"remaining_time":1.191661207},
{"learn":[0.3214451771],"iteration":888,"passed_time":9.458091792,"remaining_time":1.180931596},
{"learn":[0.3213149496],"iteration":889,"passed_time":9.468123521,"remaining_time":1.170217514},
{"learn":[0.3211877918],"iteration":890,"passed_time":9.477992358,"remaining_time":1.159485036},
{"learn":[0.3211410862],"iteration":891,"passed_time":9.487243456,"remaining_time":1.148679701},
{"learn":[0.3210448839],"iteration":892,"passed_time":9.496837087,"remaining_time":1.137918889},
{"learn":[0.3209522805],"iteration":893,"passed_time":9.506633452,"remaining_time":1.127184727},
{"learn":[0.3208550897],"iteration":894,"passed_time":9.516815078,"remaining_time":1.116497858},
{"learn":[0.3207503245],"iteration":895,"passed_time":9.526620467,"remaining_time":1.105768447},
{"learn":[0.3206838595],"iteration":896,"passed_time":9.536498551,"remaining_time":1.095049443},
{"learn":[0.3206337782],"iteration":897,"passed_time":9.547203878,"remaining_time":1.084426276},
{"learn":[0.3205174929],"iteration":898,"passed_time":9.557421741,"remaining_time":1.07374816},
{"learn":[0.3204441777],"iteration":899,"passed_time":9.568086512,"remaining_time":1.063120724},
{"learn":[0.320369528],"iteration":900,"passed_time":9.578807535,"remaining_time":1.052499385},
{"learn":[0.3202403147],"iteration":901,"passed_time":9.589366166,"remaining_time":1.041860182},
{"learn":[0.3201417995],"iteration":902,"passed_time":9.599666977,"remaining_time":1.031193463},
{"learn":[0.3200884343],"iteration":903,"passed_time":9.60992984,"remaining_time":1.020523523},
{"learn":[0.3200008696],"iteration":904,"passed_time":9.619743875,"remaining_time":1.009807368},
{"learn":[0.3199156065],"iteration":905,"passed_time":9.630277521,"remaining_time":0.9991678664},
{"learn":[0.3197981941],"iteration":906,"passed_time":9.640538417,"remaining_time":0.9885006316},
{"learn":[0.3197525195],"iteration":907,"passed_time":9.651160104,"remaining_time":0.9778708476},
{"learn":[0.3196179376],"iteration":908,"passed_time":9.661502267,"remaining_time":0.9672130983},
{"learn":[0.3194941458],"iteration":909,"passed_time":9.671791604,"remaining_time":0.9565508179},
{"learn":[0.3192509761],"iteration":910,"passed_time":9.682390555,"remaining_time":0.9459196042},
{"learn":[0.3191239094],"iteration":911,"passed_time":9.693148205,"remaining_time":0.9353037741},
{"learn":[0.3190516089],"iteration":912,"passed_time":9.703355032,"remaining_time":0.9246351455},
{"learn":[0.3189245595],"iteration":913,"passed_time":9.714038523,"remaining_time":0.9140123774},
{"learn":[0.3188785106],"iteration":914,"passed_time":9.723677629,"remaining_time":0.9032924574},
{"learn":[0.3187921052],"iteration":915,"passed_time":9.73389921,"remaining_time":0.8926283118},
{"learn":[0.3187054933],"iteration":916,"passed_time":9.745185805,"remaining_time":0.8820615287},
{"learn":[0.3185525054],"iteration":917,"passed_time":9.757387513,"remaining_time":0.8715749195},
{"learn":[0.3184642237],"iteration":918,"passed_time":9.768891956,"remaining_time":0.8610231212},
{"learn":[0.3183699346],"iteration":919,"passed_time":9.780423971,"remaining_time":0.8504716496},
{"learn":[0.318297113],"iteration":920,"passed_time":9.791723697,"remaining_time":0.8398981238},
{"learn":[0.318193894],"iteration":921,"passed_time":9.803643148,"remaining_time":0.8293754507},
{"learn":[0.3181441829],"iteration":922,"passed_time":9.814856702,"remaining_time":0.8187908625},
{"learn":[0.3180851337],"iteration":923,"passed_time":9.825983431,"remaining_time":0.8081977714},
{"learn":[0.3180023813],"iteration":924,"passed_time":9.83719644,"remaining_time":0.7976105221},
{"learn":[0.3179186882],"iteration":925,"passed_time":9.849474222,"remaining_time":0.7871070112},
{"learn":[0.3178520411],"iteration":926,"passed_time":9.861399611,"remaining_time":0.7765719219},
{"learn":[0.3178126042],"iteration":927,"passed_time":9.871698039,"remaining_time":0.7659076064},
{"learn":[0.317702843],"iteration":928,"passed_time":9.882411355,"remaining_time":0.7552757871},
{"learn":[0.3175634505],"iteration":929,"passed_time":9.893543412,"remaining_time":0.7446753106},
{"learn":[0.3174734751],"iteration":930,"passed_time":9.904028516,"remaining_time":0.7340257439},
{"learn":[0.3173439239],"iteration":931,"passed_time":9.919877244,"remaining_time":0.7237678676},
{"learn":[0.3172344363],"iteration":932,"passed_time":9.9367871,"remaining_time":0.7135742076},
{"learn":[0.3171397319],"iteration":933,"passed_time":9.951226994,"remaining_time":0.7031916291},
{"learn":[0.3169743813],"iteration":934,"passed_time":9.965031928,"remaining_time":0.6927562303},
{"learn":[0.3169161564],"iteration":935,"passed_time":9.975524137,"remaining_time":0.6820871205},
{"learn":[0.3168761251],"iteration":936,"passed_time":9.984724669,"remaining_time":0.6713315412},
{"learn":[0.316819301],"iteration":937,"passed_time":9.994497406,"remaining_time":0.6606170993},
{"learn":[0.3167386497],"iteration":938,"passed_time":10.00447896,"remaining_time":0.6499182285},
{"learn":[0.3166178352],"iteration":939,"passed_time":10.01447128,"remaining_time":0.6392215709},
{"learn":[0.3165683772],"iteration":940,"passed_time":10.02464077,"remaining_time":0.6285375192},
{"learn":[0.3164909078],"iteration":941,"passed_time":10.03490333,"remaining_time":0.6178602902},
{"learn":[0.3164206574],"iteration":942,"passed_time":10.0452235,"remaining_time":0.6071874227},
{"learn":[0.3163572435],"iteration":943,"passed_time":10.05561511,"remaining_time":0.5965195405},
{"learn":[0.3163199864],"iteration":944,"passed_time":10.06535139,"remaining_time":0.5858141023},
{"learn":[0.3162135944],"iteration":945,"passed_time":10.07581199,"remaining_time":0.5751520588},
{"learn":[0.3161696907],"iteration":946,"passed_time":10.08641264,"remaining_time":0.5644982788},
{"learn":[0.316091471],"iteration":947,"passed_time":10.09785373,"remaining_time":0.5538907108},
{"learn":[0.3160108804],"iteration":948,"passed_time":10.10920725,"remaining_time":0.5432766802},
{"learn":[0.3158987775],"iteration":949,"passed_time":10.12070871,"remaining_time":0.5326688797},
{"learn":[0.3157715092],"iteration":950,"passed_time":10.13151354,"remaining_time":0.5220233052},
{"learn":[0.3156792098],"iteration":951,"passed_time":10.14174722,"remaining_time":0.5113485994},
{"learn":[0.3156002321],"iteration":952,"passed_time":10.15230953,"remaining_time":0.5006910263},
{"learn":[0.3154946279],"iteration":953,"passed_time":10.16237586,"remaining_time":0.4900097376},
{"learn":[0.315374996],"iteration":954,"passed_time":10.17330309,"remaining_time":0.4793703025},
{"learn":[0.3152941593],"iteration":955,"passed_time":10.18279197,"remaining_time":0.4686640655},
{"learn":[0.3151647142],"iteration":956,"passed_time":10.19391155,"remaining_time":0.4580336433},
{"learn":[0.3150890121],"iteration":957,"passed_time":10.20407504,"remaining_time":0.4473602837},
{"learn":[0.3149969698],"iteration":958,"passed_time":10.21481176,"remaining_time":0.4367124944},
{"learn":[0.3148602598],"iteration":959,"passed_time":10.22592198,"remaining_time":0.4260800824},
{"learn":[0.3148206605],"iteration":960,"passed_time":10.23751994,"remaining_time":0.4154664701},
{"learn":[0.3147412093],"iteration":961,"passed_time":10.24864919,"remaining_time":0.4048322963},
{"learn":[0.3147026605],"iteration":962,"passed_time":10.25930618,"remaining_time":0.3941789498},
{"learn":[0.3145722438],"iteration":963,"passed_time":10.2708928,"remaining_time":0.3835603122},
{"learn":[0.3144739922],"iteration":964,"passed_time":10.28209832,"remaining_time":0.3729258458},
{"learn":[0.3144246798],"iteration":965,"passed_time":10.29347006,"remaining_time":0.3622960478},
{"learn":[0.3143158605],"iteration":966,"passed_time":10.30442202,"remaining_time":0.3516503897},
{"learn":[0.3142409976],"iteration":967,"passed_time":10.31848118,"remaining_time":0.3411068159},
{"learn":[0.3141592456],"iteration":968,"passed_time":10.32996417,"remaining_time":0.3304735698},
{"learn":[0.3140725297],"iteration":969,"passed_time":10.3412736,"remaining_time":0.3198332041},
{"learn":[0.3139852262],"iteration":970,"passed_time":10.35243554,"remaining_time":0.3091870552},
{"learn":[0.3138514939],"iteration":971,"passed_time":10.36306178,"remaining_time":0.2985244134},
{"learn":[0.3137842216],"iteration":972,"passed_time":10.37435638,"remaining_time":0.2878803928},
{"learn":[0.3137402541],"iteration":973,"passed_time":10.38557351,"remaining_time":0.2772329684},
{"learn":[0.3135881386],"iteration":974,"passed_time":10.39716209,"remaining_time":0.2665938998},
{"learn":[0.3134985031],"iteration":975,"passed_time":10.40852478,"remaining_time":0.2559473305},
{"learn":[0.3134351677],"iteration":976,"passed_time":10.4203054,"remaining_time":0.2453091342},
{"learn":[0.3133628676],"iteration":977,"passed_time":10.43087613,"remaining_time":0.2346413852},
{"learn":[0.3132265745],"iteration":978,"passed_time":10.44175494,"remaining_time":0.223980443},
{"learn":[0.3130861701],"iteration":979,"passed_time":10.45253375,"remaining_time":0.2133170153},
{"learn":[0.3130168888],"iteration":980,"passed_time":10.46330605,"remaining_time":0.2026532263},
{"learn":[0.3129568843],"iteration":981,"passed_time":10.47339825,"remaining_time":0.1919767501},
{"learn":[0.3128729988],"iteration":982,"passed_time":10.48367113,"remaining_time":0.1813045873},
{"learn":[0.3127743337],"iteration":983,"passed_time":10.49397559,"remaining_time":0.1706337494},
{"learn":[0.3126727218],"iteration":984,"passed_time":10.50413494,"remaining_time":0.1599614458},
{"learn":[0.3125796603],"iteration":985,"passed_time":10.51472353,"remaining_time":0.1492962773},
{"learn":[0.3124770898],"iteration":986,"passed_time":10.52515274,"remaining_time":0.1386291648},
{"learn":[0.3123835223],"iteration":987,"passed_time":10.53512483,"remaining_time":0.1279569818},
{"learn":[0.3122187951],"iteration":988,"passed_time":10.54601701,"remaining_time":0.1172964481},
{"learn":[0.3121239947],"iteration":989,"passed_time":10.55695045,"remaining_time":0.1066358631},
{"learn":[0.312057747],"iteration":990,"passed_time":10.56742835,"remaining_time":0.09597059046},
{"learn":[0.3119798465],"iteration":991,"passed_time":10.5773837,"remaining_time":0.08530148141},
{"learn":[0.3118902932],"iteration":992,"passed_time":10.58724088,"remaining_time":0.07463311799},
{"learn":[0.3118226169],"iteration":993,"passed_time":10.5972005,"remaining_time":0.063967005},
{"learn":[0.3117380714],"iteration":994,"passed_time":10.60749762,"remaining_time":0.05330400813},
{"learn":[0.3116332011],"iteration":995,"passed_time":10.61775993,"remaining_time":0.04264160614},
{"learn":[0.311571268],"iteration":996,"passed_time":10.62768663,"remaining_time":0.03197899687},
{"learn":[0.311450512],"iteration":997,"passed_time":10.6379305,"remaining_time":0.02131849799},
{"learn":[0.3112669314],"iteration":998,"passed_time":10.64800468,"remaining_time":0.01065866334},
{"learn":[0.3111879857],"iteration":999,"passed_time":10.65796514,"remaining_time":0}
]}